{"10.1109/TVCG.2013.63": {"doi": "10.1109/TVCG.2013.63", "author": ["X. Ying", "S. Xin", "Q. Sun", "Y. He"], "title": "An Intrinsic Algorithm for Parallel Poisson Disk Sampling on Arbitrary Surfaces", "year": "2013", "abstract": "Poisson disk sampling has excellent spatial and spectral properties, and plays an important role in a variety of visual computing. Although many promising algorithms have been proposed for multidimensional sampling in euclidean space, very few studies have been reported with regard to the problem of generating Poisson disks on surfaces due to the complicated nature of the surface. This paper presents an intrinsic algorithm for parallel Poisson disk sampling on arbitrary surfaces. In sharp contrast to the conventional parallel approaches, our method neither partitions the given surface into small patches nor uses any spatial data structure to maintain the voids in the sampling domain. Instead, our approach assigns each sample candidate a random and unique priority that is unbiased with regard to the distribution. Hence, multiple threads can process the candidates simultaneously and resolve conflicts by checking the given priority values. Our algorithm guarantees that the generated Poisson disks are uniformly and randomly distributed without bias. It is worth noting that our method is intrinsic and independent of the embedding space. This intrinsic feature allows us to generate Poisson disk patterns on arbitrary surfaces in IRn. To our knowledge, this is the first intrinsic, parallel, and accurate algorithm for surface Poisson disk sampling. Furthermore, by manipulating the spatially varying density function, we can obtain adaptive sampling easily.", "keywords": ["computational geometry", "differential geometry", "graphics processing units", "parallel algorithms", "spatial data structures", "intrinsic algorithm", "parallel Poisson disk sampling", "arbitrary surfaces", "spatial properties", "spectral properties", "visual computing", "multidimensional sampling", "Euclidean space", "Poisson disk generation problem", "spatial data structure", "priority values", "Poisson disk pattern generation", "spatial varying density function", "GPU", "geodesic distance", "Instruction sets", "Partitioning algorithms", "Data structures", "Approximation algorithms", "Algorithm design and analysis", "Spatial databases", "Parallel poisson disk sampling", "intrinsic algorithm", "unbiased sampling", "GPU", "geodesic distance"], "referenced_by": ["IKEY:8120299", "IKEY:7009909", "IKEY:7472145", "IKEY:9245354", "10.1145/3233310", "10.1007/s11390-015-1535-0", "10.1007/s41095-016-0057-1", "10.1016/j.cad.2013.08.016", "10.1016/j.cad.2013.08.031", "10.1016/j.cad.2014.08.023", "10.1016/j.cad.2017.05.022", "10.1016/j.cag.2014.09.015", "10.1016/j.cag.2015.11.002", "10.1016/j.cag.2018.01.001", "10.1111/cgf.12538", "10.1155/2014/943647", "10.1117/12.2179264", "10.1111/cgf.13848", "10.1016/j.solener.2020.09.061", "10.1016/j.mri.2020.11.012"], "referencing": ["IKEY:4359502", "IKEY:6143943", "IKEY:6197186", "IKEY:4342600", "IKEY:4359502", "IKEY:6143943", "IKEY:6197186", "IKEY:4342600", "IKEY:4359502", "IKEY:6143943", "IKEY:6197186", "IKEY:4342600", "10.1145/7529.8927", "10.1145/1141911.1141915", "10.1145/1640443.1640451", "10.1145/1095878.1095888", "10.1145/1141911.1141916", "10.1145/1276377.1276475", "10.1145/127719.122736", "10.1145/1360612.1360619", "10.1145/1882261.1866188", "10.1145/2010324.1964944", "10.1145/1201775.882265", "10.1145/1778765.1778816", "10.1145/2010324.1964943", "10.1145/1882261.1866189", "10.1145/2010324.1964945", "10.1145/1364901.1364919", "10.1145/571647.571648", "10.1145/1559755.1559761", "10.1145/2077378.2077401", "10.1145/325334.325182", "10.1145/7529.8927", "10.1145/1141911.1141915", "10.1145/1640443.1640451", "10.1145/1095878.1095888", "10.1145/1141911.1141916", "10.1145/1276377.1276475", "10.1145/127719.122736", "10.1145/1360612.1360619", "10.1145/1882261.1866188", "10.1145/2010324.1964944", "10.1145/1201775.882265", "10.1145/1778765.1778816", "10.1145/2010324.1964943", "10.1145/1882261.1866189", "10.1145/2010324.1964945", "10.1145/1364901.1364919", "10.1145/571647.571648", "10.1145/1559755.1559761", "10.1145/2077378.2077401", "10.1145/325334.325182", "10.1145/7529.8927", "10.1145/1141911.1141915", "10.1145/1640443.1640451", "10.1145/1095878.1095888", "10.1145/1141911.1141916", "10.1145/1276377.1276475", "10.1145/127719.122736", "10.1145/1360612.1360619", "10.1145/1882261.1866188", "10.1145/2010324.1964944", "10.1145/1201775.882265", "10.1145/1778765.1778816", "10.1145/2010324.1964943", "10.1145/1882261.1866189", "10.1145/2010324.1964945", "10.1145/1364901.1364919", "10.1145/571647.571648", "10.1145/1559755.1559761", "10.1145/2077378.2077401", "10.1145/325334.325182", "10.1080/2151237X.2011.617173", "10.1111/j.1467-8659.2012.03059.x", "10.1111/j.1467-8659.2012.03182.x", "10.1073/pnas.93.4.1591", "10.1111/j.1467-8659.2009.01499.x", "10.1016/j.cag.2012.02.005", "10.1111/j.1467-8659.2007.01100.x", "10.1080/2151237X.2011.617173", "10.1111/j.1467-8659.2012.03059.x", "10.1111/j.1467-8659.2012.03182.x", "10.1073/pnas.93.4.1591", "10.1111/j.1467-8659.2009.01499.x", "10.1016/j.cag.2012.02.005", "10.1111/j.1467-8659.2007.01100.x", "10.1080/2151237X.2011.617173", "10.1111/j.1467-8659.2012.03059.x", "10.1111/j.1467-8659.2012.03182.x", "10.1073/pnas.93.4.1591", "10.1111/j.1467-8659.2009.01499.x", "10.1016/j.cag.2012.02.005", "10.1111/j.1467-8659.2007.01100.x"]}, "10.1109/TVCG.2013.66": {"doi": "10.1109/TVCG.2013.66", "author": ["S. Kim", "R. Maciejewski", "A. Malik", "Y. Jang", "D. S. Ebert", "T. Isenberg"], "title": "Bristle Maps: A Multivariate Abstraction Technique for Geovisualization", "year": "2013", "abstract": "We present Bristle Maps, a novel method for the aggregation, abstraction, and stylization of spatiotemporal data that enables multiattribute visualization, exploration, and analysis. This visualization technique supports the display of multidimensional data by providing users with a multiparameter encoding scheme within a single visual encoding paradigm. Given a set of geographically located spatiotemporal events, we approximate the data as a continuous function using kernel density estimation. The density estimation encodes the probability that an event will occur within the space over a given temporal aggregation. These probability values, for one or more set of events, are then encoded into a bristle map. A bristle map consists of a series of straight lines that extend from, and are connected to, linear map elements such as roads, train, subway lines, and so on. These lines vary in length, density, color, orientation, and transparency\u00e2creating the multivariate attribute encoding scheme where event magnitude, change, and uncertainty can be mapped as various bristle parameters. This approach increases the amount of information displayed in a single plot and allows for unique designs for various information schemes. We show the application of our bristle map encoding scheme using categorical spatiotemporal police reports. Our examples demonstrate the use of our technique for visualizing data magnitude, variable comparisons, and a variety of multivariate attribute combinations. To evaluate the effectiveness of our bristle map, we have conducted quantitative and qualitative evaluations in which we compare our bristle map to conventional geovisualization techniques. Our results show that bristle maps are competitive in completion time and accuracy of tasks with various levels of complexity.", "keywords": ["data structures", "data visualisation", "geography", "probability", "multivariate abstraction technique", "geovisualization", "multiattribute visualization", "spatiotemporal data", "multidimensional data", "multiparameter encoding scheme", "single visual encoding paradigm", "continuous function", "kernel density estimation", "probability", "multivariate attribute encoding scheme", "bristle map encoding scheme", "Encoding", "Image color analysis", "Data visualization", "Visualization", "Equations", "Spatiotemporal phenomena", "Kernel", "Data transformation and representation", "data abstraction", "illustrative visualization", "geovisualization"], "referenced_by": ["IKEY:7588950", "IKEY:7603328", "IKEY:6876008", "IKEY:7294413", "IKEY:8078198", "IKEY:8667696", "IKEY:8809223", "10.1007/s11390-013-1383-8", "10.1007/s12650-016-0352-z", "10.1080/15230406.2013.878099", "10.1155/2014/689496", "10.1155/2016/9837123", "10.1371/journal.pone.0127088", "10.1007/978-3-030-05532-5_43", "10.1016/j.visinf.2019.03.004", "10.1007/978-3-030-32022-5_13", "10.1016/j.visinf.2020.12.001"], "referencing": ["IKEY:1249006", "IKEY:5204083", "IKEY:4658159", "IKEY:5226628", "IKEY:856996", "IKEY:4376150", "IKEY:1532144", "IKEY:1648238", "IKEY:4015426", "IKEY:4015427", "IKEY:4695829", "IKEY:4376139", "IKEY:1509075", "IKEY:7760", "IKEY:4015474", "IKEY:6155162", "IKEY:1249006", "IKEY:5204083", "IKEY:4658159", "IKEY:5226628", "IKEY:856996", "IKEY:4376150", "IKEY:1532144", "IKEY:1648238", "IKEY:4015426", "IKEY:4015427", "IKEY:4695829", "IKEY:4376139", "IKEY:1509075", "IKEY:7760", "IKEY:4015474", "IKEY:6155162", "IKEY:1249006", "IKEY:5204083", "IKEY:4658159", "IKEY:5226628", "IKEY:856996", "IKEY:4376150", "IKEY:1532144", "IKEY:1648238", "IKEY:4015426", "IKEY:4015427", "IKEY:4695829", "IKEY:4376139", "IKEY:1509075", "IKEY:7760", "IKEY:4015474", "IKEY:6155162", "10.1145/345513.345282", "10.1145/259963.260431", "10.1145/1556262.1556289", "10.1145/345513.345282", "10.1145/259963.260431", "10.1145/1556262.1556289", "10.1145/345513.345282", "10.1145/259963.260431", "10.1145/1556262.1556289", "10.1016/S0097-8493(00)00033-9", "10.1179/caj.1982.19.2.122", "10.1111/j.1540-5915.1999.tb01605.x", "10.1559/152304001782173727", "10.1057/palgrave.sj.8350066", "10.1007/978-1-4899-3324-9", "10.14714/CP13.1000", "10.2307/2685372", "10.1111/j.1467-8306.1981.tb01352.x", "10.1559/152304091783786790", "10.1179/1743277412Y.0000000007", "10.1117/12.384882", "10.1016/B978-0-08-050754-5.50012-8", "10.1016/S0097-8493(00)00033-9", "10.1179/caj.1982.19.2.122", "10.1111/j.1540-5915.1999.tb01605.x", "10.1559/152304001782173727", "10.1057/palgrave.sj.8350066", "10.1007/978-1-4899-3324-9", "10.14714/CP13.1000", "10.2307/2685372", "10.1111/j.1467-8306.1981.tb01352.x", "10.1559/152304091783786790", "10.1179/1743277412Y.0000000007", "10.1117/12.384882", "10.1016/B978-0-08-050754-5.50012-8", "10.1016/S0097-8493(00)00033-9", "10.1179/caj.1982.19.2.122", "10.1111/j.1540-5915.1999.tb01605.x", "10.1559/152304001782173727", "10.1057/palgrave.sj.8350066", "10.1007/978-1-4899-3324-9", "10.14714/CP13.1000", "10.2307/2685372", "10.1111/j.1467-8306.1981.tb01352.x", "10.1559/152304091783786790", "10.1179/1743277412Y.0000000007", "10.1117/12.384882", "10.1016/B978-0-08-050754-5.50012-8"]}, "10.1109/TVCG.2013.7": {"doi": "10.1109/TVCG.2013.7", "author": ["B. Csebfalvi"], "title": "Cosine-Weighted B-Spline Interpolation: A Fast and High-Quality Reconstruction Scheme for the Body-Centered Cubic Lattice", "year": "2013", "abstract": "In this paper, Cosine-Weighted B-spline (CWB) filters are proposed for interpolation on the optimal Body-Centered Cubic (BCC) lattice. We demonstrate that our CWB filters can well exploit the fast trilinear texture-fetching capability of modern GPUs, and outperform the state-of-the-art box-spline filters not just in terms of efficiency, but in terms of visual quality and numerical accuracy as well. Furthermore, we rigorously show that the CWB filters are better tailored to the BCC lattice than the previously proposed quasi-interpolating BCC B-spline filters, because they form a Riesz basis; exactly reproduce the original signal at the lattice points; but still provide the same approximation order.", "keywords": ["filtering theory", "graphics processing units", "image reconstruction", "image texture", "interpolation", "splines (mathematics)", "cosine weighted b-spline interpolation", "high quality reconstruction scheme", "fast quality reconstruction scheme", "body centered cubic lattice", "CWB filters", "BCC lattice", "fast trilinear texture fetching capability", "GPU", "quasiinterpolating BCC B-spline filters", "Lattices", "Splines (mathematics)", "Interpolation", "Passband", "Kernel", "Image reconstruction", "Frequency response", "Filtering", "sampling", "volume visualization", "Brain", "Computer Graphics", "Humans", "Image Processing, Computer-Assisted", "Magnetic Resonance Imaging", "Neuroimaging"], "referenced_by": ["IKEY:7784758", "10.1016/j.softx.2016.01.002", "10.1111/cgf.12364", "10.1111/cgf.12917", "10.1111/cgf.13166", "10.1111/cgf.13437"], "referencing": ["IKEY:4745632", "IKEY:817199", "IKEY:790659", "IKEY:1529680", "IKEY:4154783", "IKEY:5184830", "IKEY:1372174", "IKEY:4359498", "IKEY:346331", "IKEY:5620894", "IKEY:5482081", "IKEY:4796194", "IKEY:875199", "IKEY:5401575", "IKEY:4745632", "IKEY:817199", "IKEY:790659", "IKEY:1529680", "IKEY:4154783", "IKEY:5184830", "IKEY:1372174", "IKEY:4359498", "IKEY:346331", "IKEY:5620894", "IKEY:5482081", "IKEY:4796194", "IKEY:875199", "IKEY:5401575", "IKEY:4745632", "IKEY:817199", "IKEY:790659", "IKEY:1529680", "IKEY:4154783", "IKEY:5184830", "IKEY:1372174", "IKEY:4359498", "IKEY:346331", "IKEY:5620894", "IKEY:5482081", "IKEY:4796194", "IKEY:875199", "IKEY:5401575", "10.1111/j.1467-8659.2009.01445.x", "10.1016/j.cag.2010.02.002", "10.1016/S0019-9958(62)90633-2", "10.1111/j.1467-8659.2009.01445.x", "10.1016/j.cag.2010.02.002", "10.1016/S0019-9958(62)90633-2", "10.1111/j.1467-8659.2009.01445.x", "10.1016/j.cag.2010.02.002", "10.1016/S0019-9958(62)90633-2"]}, "10.1109/TVCG.2013.22": {"doi": "10.1109/TVCG.2013.22", "author": ["L. Vasa", "G. Brunnett"], "title": "Exploiting Connectivity to Improve the Tangential Part of Geometry Prediction", "year": "2013", "abstract": "Many algorithms have been proposed for the task of efficient compression of triangular meshes. Geometric properties of the input data are usually exploited to obtain an accurate prediction of the data at the decoder. Considerations on how to improve the prediction usually focus on its normal part, assuming that the tangential part behaves similarly. In this paper, we show that knowledge of vertex valences might allow the decoder to form a prediction that is more accurate in the tangential direction, using a weighted parallelogram prediction. This idea can be easily implemented into existing compression algorithms, such as Edgebreaker, and it can be applied at different levels of sophistication, from very simple ones, that are computationally very cheap, to some more complex ones that provide an even better compression efficiency.", "keywords": ["computational geometry", "data compression", "Internet", "mesh generation", "rendering (computer graphics)", "connectivity exploitation", "tangential geometry prediction part", "triangular mesh compression", "geometric properties", "data prediction", "vertex valences", "tangential direction", "weighted parallelogram prediction", "Edgebreaker", "computer graphics", "Web-based accelerated 3D rendering", "Prediction algorithms", "Geometry", "Decoding", "Encoding", "Shape", "Equations", "Predictive models", "Compression", "mesh", "triangle", "parallelogram", "prediction", "valence"], "referenced_by": ["IKEY:7903744", "10.1145/3377475", "10.1145/2693443", "10.1145/3300198", "10.1007/978-3-319-45123-7_26", "10.1007/s11265-015-1095-0", "10.1016/j.cad.2014.08.002", "10.1016/j.gmod.2014.09.003", "10.1111/cgf.12428", "10.1111/cgf.13044", "10.1007/s00371-019-01650-5", "10.1111/cgf.13491"], "referencing": ["IKEY:764870", "IKEY:1199602", "IKEY:841122", "IKEY:4148755", "IKEY:964504", "IKEY:1402169", "IKEY:883968", "IKEY:764870", "IKEY:1199602", "IKEY:841122", "IKEY:4148755", "IKEY:964504", "IKEY:1402169", "IKEY:883968", "IKEY:764870", "IKEY:1199602", "IKEY:841122", "IKEY:4148755", "IKEY:964504", "IKEY:1402169", "IKEY:883968", "10.1145/1090122.1090146", "10.1145/344779.344924", "10.1145/944020.944022", "10.1145/566654.566589", "10.1145/1095878.1095880", "10.1145/274363.274365", "10.1145/1090122.1090146", "10.1145/344779.344924", "10.1145/944020.944022", "10.1145/566654.566589", "10.1145/1095878.1095880", "10.1145/274363.274365", "10.1145/1090122.1090146", "10.1145/344779.344924", "10.1145/944020.944022", "10.1145/566654.566589", "10.1145/1095878.1095880", "10.1145/274363.274365", "10.1016/S0923-5965(02)00090-5", "10.1111/j.1467-8659.2005.00872.x", "10.1111/1467-8659.t01-1-00598", "10.1007/s00366-009-0162-1", "10.1111/1467-8659.00541", "10.1111/1467-8659.t01-1-00649", "10.1016/S0923-5965(02)00090-5", "10.1111/j.1467-8659.2005.00872.x", "10.1111/1467-8659.t01-1-00598", "10.1007/s00366-009-0162-1", "10.1111/1467-8659.00541", "10.1111/1467-8659.t01-1-00649", "10.1016/S0923-5965(02)00090-5", "10.1111/j.1467-8659.2005.00872.x", "10.1111/1467-8659.t01-1-00598", "10.1007/s00366-009-0162-1", "10.1111/1467-8659.00541", "10.1111/1467-8659.t01-1-00649"]}, "10.1109/TVCG.2013.62": {"doi": "10.1109/TVCG.2013.62", "author": ["J. Huang", "Z. Pan", "G. Chen", "W. Chen", "H. Bao"], "title": "Image-Space Texture-Based Output-Coherent Surface Flow Visualization", "year": "2013", "abstract": "Image-space line integral convolution (LIC) is a popular scheme for visualizing surface vector fields due to its simplicity and high efficiency. To avoid inconsistencies or color blur during the user interactions, existing approaches employ surface parameterization or 3D volume texture schemes. However, they often require expensive computation or memory cost, and cannot achieve consistent results in terms of both the granularity and color distribution on different scales. This paper introduces a novel image-space surface flow visualization approach that preserves the coherence during user interactions. To make the noise texture under different viewpoints coherent, we propose to precompute a sequence of mipmap noise textures in a coarse-to-fine manner for consistent transition, and map the textures onto each triangle with randomly assigned and constant texture coordinates. Further, a standard image-space LIC is performed to generate the flow texture. The proposed approach is simple and GPU-friendly, and can be easily combined with various texture-based flow visualization techniques. By leveraging viewpoint-dependent backward tracing and mipmap noise phase, our method can be incorporated with the image-based flow visualization (IBFV) technique for coherent visualization of unsteady flows. We demonstrate consistent and highly efficient flow visualization on a variety of data sets.", "keywords": ["computational fluid dynamics", "convolution", "flow visualisation", "graphical user interfaces", "human computer interaction", "image sequences", "image texture", "image-space texture", "output-coherent surface flow visualization", "image-space line integral convolution", "surface vector field visualization", "color blur avoidance", "inconsistency avoidance", "user interactions", "image-space surface flow visualization", "coherence preservation", "mipmap noise texture sequence", "consistent transition", "constant texture coordinates", "randomly assigned coordinates", "standard image-space LIC", "flow texture generation", "GPU-friendly approach", "viewpoint-dependent backward tracing", "mipmap noise phase", "IBFV technique", "image-based flow visualization technique", "unsteady flows", "Visualization", "Vectors", "Surface texture", "Image color analysis", "Colored noise", "Image resolution", "Flow visualization", "mipmap", "LIC", "IBFV", "surface flows", "unsteady flows"], "referenced_by": ["IKEY:6875982", "10.1002/cav.1664", "10.1016/j.cag.2017.07.014", "10.1111/cgf.12755", "10.1117/12.2080196", "10.1007/978-981-287-540-2_7"], "referencing": ["IKEY:1532850", "IKEY:5613462", "IKEY:1021575", "IKEY:4293020", "IKEY:4015497", "IKEY:1359732", "IKEY:468406", "IKEY:558044", "IKEY:346313", "IKEY:694952", "IKEY:4441709", "IKEY:4483510", "IKEY:4015401", "IKEY:5582087", "IKEY:1250363", "IKEY:1250364", "IKEY:1333662", "IKEY:6183584", "IKEY:1532850", "IKEY:5613462", "IKEY:1021575", "IKEY:4293020", "IKEY:4015497", "IKEY:1359732", "IKEY:468406", "IKEY:558044", "IKEY:346313", "IKEY:694952", "IKEY:4441709", "IKEY:4483510", "IKEY:4015401", "IKEY:5582087", "IKEY:1250363", "IKEY:1250364", "IKEY:1333662", "IKEY:6183584", "IKEY:1532850", "IKEY:5613462", "IKEY:1021575", "IKEY:4293020", "IKEY:4015497", "IKEY:1359732", "IKEY:468406", "IKEY:558044", "IKEY:346313", "IKEY:694952", "IKEY:4441709", "IKEY:4483510", "IKEY:4015401", "IKEY:5582087", "IKEY:1250363", "IKEY:1250364", "IKEY:1333662", "IKEY:6183584", "10.1145/344779.345074", "10.1145/1183287.1183297", "10.1145/1356682.1356683", "10.1145/166117.166151", "10.1145/566570.566646", "10.1145/122718.122751", "10.1145/218380.218448", "10.1145/300523.300538", "10.1145/383259.383328", "10.1145/344779.345074", "10.1145/1183287.1183297", "10.1145/1356682.1356683", "10.1145/166117.166151", "10.1145/566570.566646", "10.1145/122718.122751", "10.1145/218380.218448", "10.1145/300523.300538", "10.1145/383259.383328", "10.1145/344779.345074", "10.1145/1183287.1183297", "10.1145/1356682.1356683", "10.1145/166117.166151", "10.1145/566570.566646", "10.1145/122718.122751", "10.1145/218380.218448", "10.1145/300523.300538", "10.1145/383259.383328", "10.1002/cav.19", "10.1111/j.1467-8659.2004.00753.x", "10.1117/12.270314", "10.1007/978-3-642-59195-2_12", "10.1002/cav.19", "10.1111/j.1467-8659.2004.00753.x", "10.1117/12.270314", "10.1007/978-3-642-59195-2_12", "10.1002/cav.19", "10.1111/j.1467-8659.2004.00753.x", "10.1117/12.270314", "10.1007/978-3-642-59195-2_12"]}, "10.1109/TVCG.2013.44": {"doi": "10.1109/TVCG.2013.44", "author": ["H. Schaefer", "M. Prus", "Q. Meyer", "J. Suessmuth", "M. Stamminger"], "title": "Multiresolution Attributes for Hardware Tessellated Objects", "year": "2013", "abstract": "Hardware tessellation is one of the latest GPU features. Triangle or quad meshes are tessellated on-the-fly, where the tessellation level is chosen adaptively in a separate shader. The hardware tessellator only generates topology; attributes such as positions or texture coordinates of the newly generated vertices are determined in a domain shader. Typical applications of hardware tessellation are view dependent tessellation of parametric surfaces and displacement mapping. Often, the attributes for the newly generated vertices are stored in textures, which requires uv unwrapping, chartification, and atlas generation of the input mesh\u00e2a process that is time consuming and often requires manual intervention. In this paper, we present an alternative representation that directly stores optimized attribute values for typical hardware tessellation patterns and simply assigns these attributes to the generated vertices at render time. Using a multilevel fitting approach, the attribute values are optimized for several resolutions. Thereby, we require no parameterization, save memory by adapting the density of the samples to the content, and avoid discontinuities by construction. Our representation is optimally suited for displacement mapping: it automatically generates seamless, view-dependent displacement mapped models. The multilevel fitting approach generates better low-resolution displacement maps than simple downfiltering. By properly blending levels, we avoid artifacts such as popping or swimming surfaces. We also show other possible applications such as signal-optimized texturing or light baking. Our representation can be evaluated in a pixel shader, resulting in signal adaptive, parameterization-free texturing, comparable to PTex or Mesh Colors. Performance evaluation shows that our representation is on par with standard texture mapping and can be updated in real time, allowing for application such as interactive sculpting.", "keywords": ["graphics processing units", "mesh generation", "multiresolution attributes", "hardware tessellated objects", "GPU features", "quad meshes", "triangle meshes", "texture coordinates", "positions coordinates", "displacement mapping", "hardware tessellation patterns", "multilevel fitting approach", "pixel shader", "signal adaptive", "parameterization free texturing", "Mesh Colors", "PTex colors", "interactive sculpting", "Face", "Indexes", "Hardware", "Image color analysis", "Rendering (computer graphics)", "Interpolation", "Pipelines", "Signal-dependent storage", "hardware tessellation", "displacement mapping"], "referenced_by": ["10.1145/3072959.3073635", "10.1145/3203195", "10.1111/cgf.12714", "10.1111/cgf.12828", "10.1111/cgf.13656"], "referencing": ["IKEY:5772286", "IKEY:5772286", "IKEY:5772286", "10.1145/1330511.1330519", "10.1145/1618452.1618497", "10.1145/1661412.1618455", "10.1145/1667239.1667252", "10.1145/1731047.1731053", "10.1145/258734.258849", "10.1145/1330511.1330519", "10.1145/1618452.1618497", "10.1145/1661412.1618455", "10.1145/1667239.1667252", "10.1145/1731047.1731053", "10.1145/258734.258849", "10.1145/1330511.1330519", "10.1145/1618452.1618497", "10.1145/1661412.1618455", "10.1145/1667239.1667252", "10.1145/1731047.1731053", "10.1145/258734.258849", "10.1111/j.1467-8659.2010.01746.x", "10.1007/978-3-540-24767-8_25", "10.1111/j.1467-8659.2008.01253.x", "10.1111/j.1467-8659.2011.01991.x", "10.1016/j.cag.2011.12.001", "10.1111/j.1467-8659.2010.01746.x", "10.1007/978-3-540-24767-8_25", "10.1111/j.1467-8659.2008.01253.x", "10.1111/j.1467-8659.2011.01991.x", "10.1016/j.cag.2011.12.001", "10.1111/j.1467-8659.2010.01746.x", "10.1007/978-3-540-24767-8_25", "10.1111/j.1467-8659.2008.01253.x", "10.1111/j.1467-8659.2011.01991.x", "10.1016/j.cag.2011.12.001"]}, "10.1109/TVCG.2013.61": {"doi": "10.1109/TVCG.2013.61", "author": ["S. Bergner", "M. Sedlmair", "T. Moller", "S. N. Abdolyousefi", "A. Saad"], "title": "ParaGlide: Interactive Parameter Space Partitioning for Computer Simulations", "year": "2013", "abstract": "In this paper, we introduce ParaGlide, a visualization system designed for interactive exploration of parameter spaces of multidimensional simulation models. To get the right parameter configuration, model developers frequently have to go back and forth between setting input parameters and qualitatively judging the outcomes of their model. Current state-of-the-art tools and practices, however, fail to provide a systematic way of exploring these parameter spaces, making informed decisions about parameter configurations a tedious and workload-intensive task. ParaGlide endeavors to overcome this shortcoming by guiding data generation using a region-based user interface for parameter sampling and then dividing the model's input parameter space into partitions that represent distinct output behavior. In particular, we found that parameter space partitioning can help model developers to better understand qualitative differences among possibly high-dimensional model outputs. Further, it provides information on parameter sensitivity and facilitates comparison of models. We developed ParaGlide in close collaboration with experts from three different domains, who all were involved in developing new models for their domain. We first analyzed current practices of six domain experts and derived a set of tasks and design requirements, then engaged in a user-centered design process, and finally conducted three longitudinal in-depth case studies underlining the usefulness of our approach.", "keywords": ["data visualisation", "interactive systems", "sampling methods", "sensitivity", "user interfaces", "interactive parameter space partitioning", "computer simulations", "ParaGlide system", "visualization system", "multidimensional simulation models", "parameter configuration", "state-of-the-art tools", "workload-intensive task", "region-based user interface", "parameter sampling", "model input parameter space", "high-dimensional model outputs", "parameter sensitivity", "domain experts", "design requirements", "user-centered design process", "longitudinal in-depth case studies", "Computational modeling", "Biological system modeling", "Data models", "Analytical models", "Image segmentation", "Mathematical model", "Animals", "Computer simulation", "parameter space partitioning", "region-based experimental design", "similarity-based embedding", "interactive visual analysis", "Brain", "Cluster Analysis", "Computer Graphics", "Computer Simulation", "Diagnostic Imaging", "Humans", "Image Processing, Computer-Assisted", "Models, Theoretical", "Reproducibility of Results", "Software", "User-Computer Interface"], "referenced_by": ["IKEY:7429486", "IKEY:6876043", "IKEY:6876045", "IKEY:7352365", "IKEY:7536133", "IKEY:7552504", "IKEY:7347635", "IKEY:7883516", "IKEY:7347629", "IKEY:8440820", "IKEY:8632312", "IKEY:8805426", "10.1007/s00371-015-1096-9", "10.1007/s00791-015-0241-3", "10.1007/s12209-015-2605-7", "10.1016/j.ascom.2016.09.002", "10.1111/cgf.12654", "10.1111/cgf.13415", "10.1186/1471-2105-16-S11-S9", "10.1016/j.visinf.2019.08.002", "10.1016/j.cagx.2019.100010", "10.1111/cgf.13894"], "referencing": ["IKEY:6065007", "IKEY:6327248", "IKEY:6064952", "IKEY:1423126", "IKEY:5613467", "IKEY:1704833", "IKEY:4069243", "IKEY:6065007", "IKEY:6327248", "IKEY:6064952", "IKEY:1423126", "IKEY:5613467", "IKEY:1704833", "IKEY:4069243", "IKEY:6065007", "IKEY:6327248", "IKEY:6064952", "IKEY:1423126", "IKEY:5613467", "IKEY:1704833", "IKEY:4069243", "10.1145/258734.258887", "10.1145/1168149.1168158", "10.1145/258734.258887", "10.1145/1168149.1168158", "10.1145/258734.258887", "10.1145/1168149.1168158", "10.1007/s11222-007-9033-z", "10.1007/978-3-540-75759-7_61", "10.1016/S0167-739X(98)00047-8", "10.1023/A:1007472602017", "10.1037/0033-295X.113.1.57", "10.1007/978-3-540-85988-8_30", "10.1177/1473871611413099", "10.1111/j.1467-8659.2011.01940.x", "10.1007/3-540-45783-6_52", "10.1007/3-540-28349-8_2", "10.1115/1.2897009", "10.1111/j.1467-8659.2012.03116.x", "10.1016/j.jcp.2006.10.011", "10.2307/1932409", "10.1007/s00285-009-0311-6", "10.1007/s00332-002-0510-4", "10.1007/s11222-007-9033-z", "10.1007/978-3-540-75759-7_61", "10.1016/S0167-739X(98)00047-8", "10.1023/A:1007472602017", "10.1037/0033-295X.113.1.57", "10.1007/978-3-540-85988-8_30", "10.1177/1473871611413099", "10.1111/j.1467-8659.2011.01940.x", "10.1007/3-540-45783-6_52", "10.1007/3-540-28349-8_2", "10.1115/1.2897009", "10.1111/j.1467-8659.2012.03116.x", "10.1016/j.jcp.2006.10.011", "10.2307/1932409", "10.1007/s00285-009-0311-6", "10.1007/s00332-002-0510-4", "10.1007/s11222-007-9033-z", "10.1007/978-3-540-75759-7_61", "10.1016/S0167-739X(98)00047-8", "10.1023/A:1007472602017", "10.1037/0033-295X.113.1.57", "10.1007/978-3-540-85988-8_30", "10.1177/1473871611413099", "10.1111/j.1467-8659.2011.01940.x", "10.1007/3-540-45783-6_52", "10.1007/3-540-28349-8_2", "10.1115/1.2897009", "10.1111/j.1467-8659.2012.03116.x", "10.1016/j.jcp.2006.10.011", "10.2307/1932409", "10.1007/s00285-009-0311-6", "10.1007/s00332-002-0510-4"]}, "10.1109/TVCG.2013.71": {"doi": "10.1109/TVCG.2013.71", "author": ["D. Kim", "J. Lee", "J. Lee", "I. Shin", "J. Kim", "S. Yoon"], "title": "Scheduling in Heterogeneous Computing Environments for Proximity Queries", "year": "2013", "abstract": "We present a novel, linear programming (LP)-based scheduling algorithm that exploits heterogeneous multicore architectures such as CPUs and GPUs to accelerate a wide variety of proximity queries. To represent complicated performance relationships between heterogeneous architectures and different computations of proximity queries, we propose a simple, yet accurate model that measures the expected running time of these computations. Based on this model, we formulate an optimization problem that minimizes the largest time spent on computing resources, and propose a novel, iterative LP-based scheduling algorithm. Since our method is general, we are able to apply our method into various proximity queries used in five different applications that have different characteristics. Our method achieves an order of magnitude performance improvement by using four different GPUs and two hexa-core CPUs over using a hexa-core CPU only. Unlike prior scheduling methods, our method continually improves the performance, as we add more computing resources. Also, our method achieves much higher performance improvement compared with prior methods as heterogeneity of computing resources is increased. Moreover, for one of tested applications, our method achieves even higher performance than a prior parallel method optimized manually for the application. We also show that our method provides results that are close (e.g., 75 percent) to the performance provided by a conservative upper bound of the ideal throughput. These results demonstrate the efficiency and robustness of our algorithm that have not been achieved by prior methods. In addition, we integrate one of our contributions with a work stealing method. Our version of the work stealing method achieves 18 percent performance improvement on average over the original work stealing method. This result shows wide applicability of our approach.", "keywords": ["computer architecture", "graphics processing units", "linear programming", "multiprocessing systems", "optimisation", "query processing", "scheduling", "heterogeneous computing environments", "proximity queries", "scheduling", "linear programming", "LP based scheduling algorithm", "multicore architectures", "GPU", "CPU", "heterogeneous architectures", "optimization problem", "magnitude performance improvement", "computing resources", "work stealing method", "Computational modeling", "Multicore processing", "Scheduling algorithms", "Optimization", "Acceleration", "Heterogeneous system", "proximity query", "scheduling", "collision detection", "ray tracing", "motion planning"], "referenced_by": ["10.5626/JCSE.2015.9.4.204", "10.1007/s00607-020-00846-1"], "referencing": ["IKEY:660313", "IKEY:4061547", "IKEY:5740825", "IKEY:5457293", "IKEY:4492769", "IKEY:993206", "IKEY:365680", "IKEY:5493485", "IKEY:5749745", "IKEY:5470804", "IKEY:660313", "IKEY:4061547", "IKEY:5740825", "IKEY:5457293", "IKEY:4492769", "IKEY:993206", "IKEY:365680", "IKEY:5493485", "IKEY:5749745", "IKEY:5470804", "IKEY:660313", "IKEY:4061547", "IKEY:5740825", "IKEY:5457293", "IKEY:4492769", "IKEY:993206", "IKEY:365680", "IKEY:5493485", "IKEY:5749745", "IKEY:5470804", "10.1145/2070752.2024203", "10.1145/1278480.1278667", "10.1145/1383422.1383447", "10.1145/237502.237576", "10.1145/1816038.1815998", "10.1145/1629255.1629303", "10.1145/2070752.2024203", "10.1145/1278480.1278667", "10.1145/1383422.1383447", "10.1145/237502.237576", "10.1145/1816038.1815998", "10.1145/1629255.1629303", "10.1145/2070752.2024203", "10.1145/1278480.1278667", "10.1145/1383422.1383447", "10.1145/237502.237576", "10.1145/1816038.1815998", "10.1145/1629255.1629303", "10.1007/BF02579150", "10.1017/CBO9780511804441", "10.1017/CBO9780511546877", "10.1007/978-3-642-23400-2_20", "10.1002/cav.359", "10.1002/cpe.1631", "10.1016/0166-218X(85)90009-5", "10.1007/BF01585745", "10.1016/j.orl.2004.05.004", "10.1006/jpdc.1996.0107", "10.1111/j.1467-8659.2009.01556.x", "10.1007/978-3-642-15291-7_23", "10.1111/j.1467-8659.2009.01611.x", "10.1111/j.1467-8659.2009.01378.x", "10.1007/BF02579150", "10.1017/CBO9780511804441", "10.1017/CBO9780511546877", "10.1007/978-3-642-23400-2_20", "10.1002/cav.359", "10.1002/cpe.1631", "10.1016/0166-218X(85)90009-5", "10.1007/BF01585745", "10.1016/j.orl.2004.05.004", "10.1006/jpdc.1996.0107", "10.1111/j.1467-8659.2009.01556.x", "10.1007/978-3-642-15291-7_23", "10.1111/j.1467-8659.2009.01611.x", "10.1111/j.1467-8659.2009.01378.x", "10.1007/BF02579150", "10.1017/CBO9780511804441", "10.1017/CBO9780511546877", "10.1007/978-3-642-23400-2_20", "10.1002/cav.359", "10.1002/cpe.1631", "10.1016/0166-218X(85)90009-5", "10.1007/BF01585745", "10.1016/j.orl.2004.05.004", "10.1006/jpdc.1996.0107", "10.1111/j.1467-8659.2009.01556.x", "10.1007/978-3-642-15291-7_23", "10.1111/j.1467-8659.2009.01611.x", "10.1111/j.1467-8659.2009.01378.x"]}, "10.1109/TVCG.2013.65": {"doi": "10.1109/TVCG.2013.65", "author": ["A. Mayorga", "M. Gleicher"], "title": "Splatterplots: Overcoming Overdraw in Scatter Plots", "year": "2013", "abstract": "We introduce Splatterplots, a novel presentation of scattered data that enables visualizations that scale beyond standard scatter plots. Traditional scatter plots suffer from overdraw (overlapping glyphs) as the number of points per unit area increases. Overdraw obscures outliers, hides data distributions, and makes the relationship among subgroups of the data difficult to discern. To address these issues, Splatterplots abstract away information such that the density of data shown in any unit of screen space is bounded, while allowing continuous zoom to reveal abstracted details. Abstraction automatically groups dense data points into contours and samples remaining points. We combine techniques for abstraction with perceptually based color blending to reveal the relationship between data subgroups. The resulting visualizations represent the dense regions of each subgroup of the data set as smooth closed shapes and show representative outliers explicitly. We present techniques that leverage the GPU for Splatterplot computation and rendering, enabling interaction with massive data sets. We show how Splatterplots can be an effective alternative to traditional methods of displaying scatter data communicating data trends, outliers, and data set relationships much like traditional scatter plots, but scaling to data sets of higher density and up to millions of points on the screen.", "keywords": ["data visualisation", "graphics processing units", "scatter plots", "scattered data", "overlapping glyphs", "data distributions", "screen space", "abstracted details", "data subgroups", "GPU", "Splatterplot computation", "Splatterplot rendering", "Visualization", "Image color analysis", "Data visualization", "Encoding", "Shape", "Clutter", "Scalability issues", "visual design", "perception theory", "statistical graphics"], "referenced_by": ["IKEY:7574924", "IKEY:7348077", "IKEY:7043852", "IKEY:7515942", "IKEY:6875930", "IKEY:6875982", "IKEY:7536212", "IKEY:7784854", "IKEY:7817898", "IKEY:7852440", "IKEY:7864468", "IKEY:8017602", "IKEY:8019866", "IKEY:8019882", "IKEY:7883508", "IKEY:6785790", "IKEY:7930525", "IKEY:8047300", "IKEY:8440091", "IKEY:8440817", "IKEY:8667672", "IKEY:8383983", "IKEY:8848845", "IKEY:8809844", "IKEY:8820172", "IKEY:8807244", "IKEY:8812988", "IKEY:8693735", "IKEY:9146191", "IKEY:9308625", "10.1145/2702123.2702585", "10.1145/2702123.2702509", "10.1145/3360721", "10.1002/rcm.7823", "10.1016/j.cag.2018.02.008", "10.1016/j.jvlc.2016.07.003", "10.1080/15230406.2016.1174623", "10.1111/cgf.12386", "10.1111/cgf.12845", "10.1111/cgf.12877", "10.1111/cgf.12929", "10.1111/cgf.13176", "10.1111/cgf.13391", "10.1177/1473871617698517", "10.15748/jasse.2.292", "10.3390/sym8120152", "10.1261/rna.064493.117", "10.1111/cgf.13404", "10.1111/cgf.13408", "10.4316/AECE.2018.04008", "10.1007/978-3-030-03490-0_10", "10.3390/computers8010012", "10.1007/978-3-662-45289-9_17", "10.1007/s12650-019-00569-2", "10.1002/joc.6404", "10.1016/j.cag.2020.05.028", "10.1007/s12650-020-00694-3", "10.1038/s41598-020-73402-8", "10.1007/s41095-020-0197-1"], "referencing": ["IKEY:5290769", "IKEY:4178161", "IKEY:4376150", "IKEY:5290706", "IKEY:1028760", "IKEY:4376143", "IKEY:5613442", "IKEY:4376149", "IKEY:4658123", "IKEY:5429604", "IKEY:4906843", "IKEY:4658159", "IKEY:5290769", "IKEY:4178161", "IKEY:4376150", "IKEY:5290706", "IKEY:1028760", "IKEY:4376143", "IKEY:5613442", "IKEY:4376149", "IKEY:4658123", "IKEY:5429604", "IKEY:4906843", "IKEY:4658159", "IKEY:5290769", "IKEY:4178161", "IKEY:4376150", "IKEY:5290706", "IKEY:1028760", "IKEY:4376143", "IKEY:5613442", "IKEY:4376149", "IKEY:4658123", "IKEY:5429604", "IKEY:4906843", "IKEY:4658159", "10.1145/1556262.1556289", "10.1145/1753326.1753714", "10.1145/1111411.1111431", "10.1145/1870076.1870080", "10.1145/1556262.1556289", "10.1145/1753326.1753714", "10.1145/1111411.1111431", "10.1145/1870076.1870080", "10.1145/1556262.1556289", "10.1145/1753326.1753714", "10.1145/1111411.1111431", "10.1145/1870076.1870080", "10.1179/000870403235002042", "10.2307/2683294", "10.1117/12.384882", "10.1111/j.1467-8659.2009.01452.x", "10.1057/palgrave.ivs.9500122", "10.1057/ivs.2009.34", "10.1111/j.1467-8659.2009.01467.x", "10.1198/106186008X320465", "10.1111/j.1467-8659.2009.01694.x", "10.1057/ivs.2010.4", "10.1167/9.2.13", "10.1167/2.4.5", "10.1167/6.12.7", "10.1137/1.9781611971712", "10.1167/7.2.17", "10.1111/j.1467-8659.2011.01922.x", "10.1179/000870403235002042", "10.2307/2683294", "10.1117/12.384882", "10.1111/j.1467-8659.2009.01452.x", "10.1057/palgrave.ivs.9500122", "10.1057/ivs.2009.34", "10.1111/j.1467-8659.2009.01467.x", "10.1198/106186008X320465", "10.1111/j.1467-8659.2009.01694.x", "10.1057/ivs.2010.4", "10.1167/9.2.13", "10.1167/2.4.5", "10.1167/6.12.7", "10.1137/1.9781611971712", "10.1167/7.2.17", "10.1111/j.1467-8659.2011.01922.x", "10.1179/000870403235002042", "10.2307/2683294", "10.1117/12.384882", "10.1111/j.1467-8659.2009.01452.x", "10.1057/palgrave.ivs.9500122", "10.1057/ivs.2009.34", "10.1111/j.1467-8659.2009.01467.x", "10.1198/106186008X320465", "10.1111/j.1467-8659.2009.01694.x", "10.1057/ivs.2010.4", "10.1167/9.2.13", "10.1167/2.4.5", "10.1167/6.12.7", "10.1137/1.9781611971712", "10.1167/7.2.17", "10.1111/j.1467-8659.2011.01922.x"]}, "10.1109/TVCG.2012.177": {"doi": "10.1109/TVCG.2012.177", "author": ["B. Li", "X. Li", "K. Wang", "H. Qin"], "title": "Surface Mesh to Volumetric Spline Conversion with Generalized Polycubes", "year": "2013", "abstract": "This paper develops a novel volumetric parameterization and spline construction framework, which is an effective modeling tool for converting surface meshes to volumetric splines. Our new splines are defined upon a novel parametric domain called generalized polycubes (GPCs). A GPC comprises a set of regular cube domains topologically glued together. Compared with conventional polycubes (CPCs), the GPC is much more powerful and flexible and has improved numerical accuracy and computational efficiency when serving as a parametric domain. We design an automatic algorithm to construct the GPC domain while also permitting the user to improve shape abstraction via interactive intervention. We then parameterize the input model on the GPC domain. Finally, we devise a new volumetric spline scheme based on this seamless volumetric parameterization. With a hierarchical fitting scheme, the proposed splines can fit data accurately using reduced number of superfluous control points. Our volumetric modeling scheme has great potential in shape modeling, engineering analysis, and reverse engineering applications.", "keywords": ["computational geometry", "mesh generation", "splines (mathematics)", "surface mesh", "volumetric spline conversion", "generalized polycubes", "novel volumetric parameterization", "spline construction framework", "GPC", "conventional polycubes", "CPC", "computational efficiency", "numerical accuracy", "shape abstraction", "interactive intervention", "superfluous control points", "volumetric modeling scheme", "engineering analysis", "reverse engineering applications", "shape modeling", "Splines (mathematics)", "Shape", "Solid modeling", "Computational modeling", "Solids", "Topology", "Algorithm design and analysis", "Volumetric spline", "generalized polycube", "volumetric parameterization"], "referenced_by": ["IKEY:7250335", "IKEY:6634117", "IKEY:7226867", "10.1145/2659467.2659469", "10.1145/2668020", "10.1145/3313797", "10.1145/2766941", "10.1145/3130800.3130848", "10.1145/3386569.3392378", "10.1007/s10543-017-0669-6", "10.1007/s12021-014-9259-9", "10.1016/j.cad.2013.08.018", "10.1016/j.cad.2014.08.020", "10.1016/j.cad.2017.05.002", "10.1016/j.cma.2014.10.046", "10.1016/j.cma.2015.06.020", "10.1016/j.cma.2016.04.028", "10.1016/j.cma.2016.09.030", "10.1016/j.matchemphys.2013.12.028", "10.1016/j.media.2015.01.005", "10.1016/j.neuroimage.2016.12.014", "10.1111/cgf.12166", "10.1111/cgf.12273", "10.1115/1.4040773", "10.1007/978-3-642-41083-3_3", "10.1007/978-3-642-41083-3_4"], "referencing": ["IKEY:5887329", "IKEY:1398778", "IKEY:5521444", "IKEY:1298797", "IKEY:4738453", "IKEY:4390940", "IKEY:4273380", "IKEY:5887329", "IKEY:1398778", "IKEY:5521444", "IKEY:1298797", "IKEY:4738453", "IKEY:4390940", "IKEY:4273380", "IKEY:5887329", "IKEY:1398778", "IKEY:5521444", "IKEY:1298797", "IKEY:4738453", "IKEY:4390940", "IKEY:4273380", "10.1145/1015706.1015810", "10.1145/1364901.1364958", "10.1145/1944745.1944771", "10.1145/1281500.1281510", "10.1145/1236246.1236263", "10.1145/1186822.1073229", "10.1145/1276377.1276466", "10.1145/1073204.1073219", "10.1145/1839778.1839796", "10.1145/1060244.1060253", "10.1145/882262.882295", "10.1145/1015706.1015715", "10.1145/1101389.1101468", "10.1145/218380.218473", "10.1145/1057432.1057456", "10.1145/1015706.1015810", "10.1145/1364901.1364958", "10.1145/1944745.1944771", "10.1145/1281500.1281510", "10.1145/1236246.1236263", "10.1145/1186822.1073229", "10.1145/1276377.1276466", "10.1145/1073204.1073219", "10.1145/1839778.1839796", "10.1145/1060244.1060253", "10.1145/882262.882295", "10.1145/1015706.1015715", "10.1145/1101389.1101468", "10.1145/218380.218473", "10.1145/1057432.1057456", "10.1145/1015706.1015810", "10.1145/1364901.1364958", "10.1145/1944745.1944771", "10.1145/1281500.1281510", "10.1145/1236246.1236263", "10.1145/1186822.1073229", "10.1145/1276377.1276466", "10.1145/1073204.1073219", "10.1145/1839778.1839796", "10.1145/1060244.1060253", "10.1145/882262.882295", "10.1145/1015706.1015715", "10.1145/1101389.1101468", "10.1145/218380.218473", "10.1145/1057432.1057456", "10.1016/j.cma.2004.10.008", "10.1016/j.cag.2012.03.007", "10.1016/j.cag.2010.03.011", "10.1016/j.cagd.2008.09.008", "10.1016/j.cma.2007.02.009", "10.1016/j.cad.2008.01.012", "10.1016/j.cag.2009.03.024", "10.1111/j.1467-8659.2007.01103.x", "10.1007/s00371-007-0197-5", "10.1111/j.1467-8659.2009.01379.x", "10.1111/j.1467-8659.2008.01273.x", "10.1007/978-3-540-79246-8_1", "10.1111/j.1467-8659.2011.02015.x", "10.1007/3-540-26808-1_9", "10.1561/0600000011", "10.1016/S0167-8396(03)00002-5", "10.1111/j.1467-8659.2011.02014.x", "10.1007/s00371-004-0277-8", "10.1007/s00366-009-0168-8", "10.1016/j.cma.2004.10.008", "10.1016/j.cag.2012.03.007", "10.1016/j.cag.2010.03.011", "10.1016/j.cagd.2008.09.008", "10.1016/j.cma.2007.02.009", "10.1016/j.cad.2008.01.012", "10.1016/j.cag.2009.03.024", "10.1111/j.1467-8659.2007.01103.x", "10.1007/s00371-007-0197-5", "10.1111/j.1467-8659.2009.01379.x", "10.1111/j.1467-8659.2008.01273.x", "10.1007/978-3-540-79246-8_1", "10.1111/j.1467-8659.2011.02015.x", "10.1007/3-540-26808-1_9", "10.1561/0600000011", "10.1016/S0167-8396(03)00002-5", "10.1111/j.1467-8659.2011.02014.x", "10.1007/s00371-004-0277-8", "10.1007/s00366-009-0168-8", "10.1016/j.cma.2004.10.008", "10.1016/j.cag.2012.03.007", "10.1016/j.cag.2010.03.011", "10.1016/j.cagd.2008.09.008", "10.1016/j.cma.2007.02.009", "10.1016/j.cad.2008.01.012", "10.1016/j.cag.2009.03.024", "10.1111/j.1467-8659.2007.01103.x", "10.1007/s00371-007-0197-5", "10.1111/j.1467-8659.2009.01379.x", "10.1111/j.1467-8659.2008.01273.x", "10.1007/978-3-540-79246-8_1", "10.1111/j.1467-8659.2011.02015.x", "10.1007/3-540-26808-1_9", "10.1561/0600000011", "10.1016/S0167-8396(03)00002-5", "10.1111/j.1467-8659.2011.02014.x", "10.1007/s00371-004-0277-8", "10.1007/s00366-009-0168-8"]}, "10.1109/TVCG.2013.67": {"doi": "10.1109/TVCG.2013.67", "author": ["S. Hauswiesner", "M. Straka", "G. Reitmayr"], "title": "Virtual Try-On through Image-Based Rendering", "year": "2013", "abstract": "Virtual try-on applications have become popular because they allow users to watch themselves wearing different clothes without the effort of changing them physically. This helps users to make quick buying decisions and, thus, improves the sales efficiency of retailers. Previous solutions usually involve motion capture, 3D reconstruction or modeling, which are time consuming and not robust for all body poses. Our method avoids these steps by combining image-based renderings of the user and previously recorded garments. It transfers the appearance of a garment recorded from one user to another by matching input and recorded frames, image-based visual hull rendering, and online registration methods. Using images of real garments allows for a realistic rendering quality with high performance. It is suitable for a wide range of clothes and complex appearances, allows arbitrary viewing angles, and requires only little manual input. Our system is particularly useful for virtual try-on applications as well as interactive games.", "keywords": ["clothing", "computer games", "image processing", "interactive systems", "rendering (computer graphics)", "virtual reality", "image based rendering", "virtual try-on applications", "buying decisions", "sales efficiency", "3D reconstruction", "recorded garments", "online registration methods", "image based visual hull rendering", "interactive games", "Databases", "Rendering (computer graphics)", "Feature extraction", "Runtime", "Mixed reality", "augmented reality", "image-based rendering", "virtual try-on", "Algorithms", "Clothing", "Computer Graphics", "Female", "Humans", "Imaging, Three-Dimensional", "Male", "User-Computer Interface"], "referenced_by": ["IKEY:8265474", "IKEY:7177402", "IKEY:7385813", "IKEY:7331174", "IKEY:7782720", "IKEY:8298525", "IKEY:8632636", "IKEY:8636265", "IKEY:8468063", "IKEY:8770290", "IKEY:9022010", "IKEY:9156594", "10.1145/2634212", "10.1007/978-3-319-48511-9_11", "10.1007/978-981-10-6364-0_78", "10.1007/s00371-016-1232-1", "10.1016/B978-0-08-101217-8.00002-6", "10.1016/j.cag.2014.06.001", "10.1016/j.jmsy.2014.05.006", "10.1201/b18154-30", "10.1007/s11042-018-5983-8", "10.1016/j.cad.2018.08.002", "10.1007/s11042-018-5711-4", "10.1007/s11554-018-0825-5", "10.1115/1.4042102", "10.1111/cgf.13643", "10.1108/ITP-02-2019-0092", "10.1007/978-3-030-36922-4_2", "10.1155/2020/1314598", "10.1016/j.cag.2020.06.002", "10.1007/s11042-020-09989-x", "10.1177/0040517520970169"], "referencing": ["IKEY:4250473", "IKEY:4079267", "IKEY:6165146", "IKEY:781210", "IKEY:4359478", "IKEY:5995316", "IKEY:6162885", "IKEY:1335262", "IKEY:4250473", "IKEY:4079267", "IKEY:6165146", "IKEY:781210", "IKEY:4359478", "IKEY:5995316", "IKEY:6162885", "IKEY:1335262", "IKEY:4250473", "IKEY:4079267", "IKEY:6165146", "IKEY:781210", "IKEY:4359478", "IKEY:5995316", "IKEY:6162885", "IKEY:1335262", "10.1145/1661412.1618520", "10.1145/1882262.1866161", "10.1145/2407746.2407779", "10.1145/2024156.2024164", "10.1145/1944745.1944776", "10.1145/344779.344951", "10.1145/1964921.1964935", "10.1145/1833349.1778843", "10.1145/1399504.1360698", "10.1145/1661412.1618520", "10.1145/1882262.1866161", "10.1145/2407746.2407779", "10.1145/2024156.2024164", "10.1145/1944745.1944776", "10.1145/344779.344951", "10.1145/1964921.1964935", "10.1145/1833349.1778843", "10.1145/1399504.1360698", "10.1145/1661412.1618520", "10.1145/1882262.1866161", "10.1145/2407746.2407779", "10.1145/2024156.2024164", "10.1145/1944745.1944776", "10.1145/344779.344951", "10.1145/1964921.1964935", "10.1145/1833349.1778843", "10.1145/1399504.1360698", "10.1016/j.cag.2010.07.008", "10.1080/16864360.2005.10738329", "10.1016/j.compind.2011.04.002", "10.1007/978-3-642-01811-4_9", "10.1007/978-3-642-21227-7_59", "10.1007/978-3-7091-6453-2_10", "10.1137/1028154", "10.1016/j.cag.2010.07.008", "10.1080/16864360.2005.10738329", "10.1016/j.compind.2011.04.002", "10.1007/978-3-642-01811-4_9", "10.1007/978-3-642-21227-7_59", "10.1007/978-3-7091-6453-2_10", "10.1137/1028154", "10.1016/j.cag.2010.07.008", "10.1080/16864360.2005.10738329", "10.1016/j.compind.2011.04.002", "10.1007/978-3-642-01811-4_9", "10.1007/978-3-642-21227-7_59", "10.1007/978-3-7091-6453-2_10", "10.1137/1028154"]}, "10.1109/TVCG.2013.21": {"doi": "10.1109/TVCG.2013.21", "author": ["Y. Wu", "Y. Chuang"], "title": "VisibilityCluster: Average Directional Visibility for Many-Light Rendering", "year": "2013", "abstract": "This paper proposes the VisibilityCluster algorithm for efficient visibility approximation and representation in many-light rendering. By carefully clustering lights and shading points, we can construct a visibility matrix that exhibits good local structures due to visibility coherence of nearby lights and shading points. Average visibility can be efficiently estimated by exploiting the sparse structure of the matrix and shooting only few shadow rays between clusters. Moreover, we can use the estimated average visibility as a quality measure for visibility estimation, enabling us to locally refine VisibilityClusters with large visibility variance for improving accuracy. We demonstrate that, with the proposed method, visibility can be incorporated into importance sampling at a reasonable cost for the many-light problem, significantly reducing variance in Monte Carlo rendering. In addition, the proposed method can be used to increase realism of local shading by adding directional occlusion effects. Experiments show that the proposed technique outperforms state-of-the-art importance sampling algorithms, and successfully enhances the preview quality for lighting design.", "keywords": ["approximation theory", "importance sampling", "lighting", "rendering (computer graphics)", "sparse matrices", "average directional visibility", "VisibilityCluster algorithm", "visibility approximation", "visibility representation", "many-light rendering", "light clustering", "shading points", "visibility matrix", "local structures", "visibility coherence", "sparse matrix structure", "shadow rays", "visibility estimation", "quality measure", "large visibility variance", "accuracy improvement", "importance sampling", "many-light problem", "Monte Carlo rendering", "variance reduction", "local shading", "directional occlusion effects", "lighting design preview quality enhancement", "Monte Carlo methods", "Lighting", "Rendering (computer graphics)", "Approximation methods", "Approximation algorithms", "Coherence", "Geometry", "Ray tracing", "visibility approximation", "importance sampling", "the many-light problem", "Algorithms", "Cluster Analysis", "Image Processing, Computer-Assisted", "Lighting"], "referenced_by": ["IKEY:6994841", "IKEY:8341814", "10.1145/3197517.3201340", "10.1007/s00371-017-1449-7", "10.1111/cgf.12584", "10.1111/cgf.13040", "10.1007/s41095-019-0137-0", "10.1111/cgf.13776", "10.1111/cgf.14053"], "referencing": ["IKEY:5962103", "IKEY:1608022", "IKEY:4061555", "IKEY:5962103", "IKEY:1608022", "IKEY:4061555", "IKEY:5962103", "IKEY:1608022", "IKEY:4061555", "10.1145/226150.226151", "10.1145/311535.311551", "10.1145/2231816.2231819", "10.1145/1507149.1507161", "10.1145/2070781.2024214", "10.1145/1409060.1409081", "10.1145/258734.258769", "10.1145/1073204.1073318", "10.1145/1141911.1141997", "10.1145/2185520.2335399", "10.1145/1882262.1866169", "10.1145/2070781.2024180", "10.1145/1053427.1053460", "10.1145/1111411.1111428", "10.1145/1507149.1507162", "10.1145/1409060.1409082", "10.1145/1609967.1609971", "10.1145/344779.344954", "10.1145/882262.882314", "10.1145/1015706.1015751", "10.1145/1073204.1073328", "10.1145/226150.226151", "10.1145/311535.311551", "10.1145/2231816.2231819", "10.1145/1507149.1507161", "10.1145/2070781.2024214", "10.1145/1409060.1409081", "10.1145/258734.258769", "10.1145/1073204.1073318", "10.1145/1141911.1141997", "10.1145/2185520.2335399", "10.1145/1882262.1866169", "10.1145/2070781.2024180", "10.1145/1053427.1053460", "10.1145/1111411.1111428", "10.1145/1507149.1507162", "10.1145/1409060.1409082", "10.1145/1609967.1609971", "10.1145/344779.344954", "10.1145/882262.882314", "10.1145/1015706.1015751", "10.1145/1073204.1073328", "10.1145/226150.226151", "10.1145/311535.311551", "10.1145/2231816.2231819", "10.1145/1507149.1507161", "10.1145/2070781.2024214", "10.1145/1409060.1409081", "10.1145/258734.258769", "10.1145/1073204.1073318", "10.1145/1141911.1141997", "10.1145/2185520.2335399", "10.1145/1882262.1866169", "10.1145/2070781.2024180", "10.1145/1053427.1053460", "10.1145/1111411.1111428", "10.1145/1507149.1507162", "10.1145/1409060.1409082", "10.1145/1609967.1609971", "10.1145/344779.344954", "10.1145/882262.882314", "10.1145/1015706.1015751", "10.1145/1073204.1073328", "10.1080/2151237X.2006.10129211", "10.1007/978-3-7091-6453-2_6", "10.1111/j.1467-8659.2011.01861.x", "10.1007/s00371-006-0055-x", "10.1007/s00371-008-0227-y", "10.1111/j.1467-8659.2008.01250.x", "10.1111/j.1467-8659.2008.01249.x", "10.1111/j.1467-8659.2009.01366.x", "10.1111/j.1467-8659.2012.03049.x", "10.1111/j.1467-8659.2008.01166.x", "10.1111/j.1467-8659.2009.01398.x", "10.1080/2151237X.2006.10129211", "10.1007/978-3-7091-6453-2_6", "10.1111/j.1467-8659.2011.01861.x", "10.1007/s00371-006-0055-x", "10.1007/s00371-008-0227-y", "10.1111/j.1467-8659.2008.01250.x", "10.1111/j.1467-8659.2008.01249.x", "10.1111/j.1467-8659.2009.01366.x", "10.1111/j.1467-8659.2012.03049.x", "10.1111/j.1467-8659.2008.01166.x", "10.1111/j.1467-8659.2009.01398.x", "10.1080/2151237X.2006.10129211", "10.1007/978-3-7091-6453-2_6", "10.1111/j.1467-8659.2011.01861.x", "10.1007/s00371-006-0055-x", "10.1007/s00371-008-0227-y", "10.1111/j.1467-8659.2008.01250.x", "10.1111/j.1467-8659.2008.01249.x", "10.1111/j.1467-8659.2009.01366.x", "10.1111/j.1467-8659.2012.03049.x", "10.1111/j.1467-8659.2008.01166.x", "10.1111/j.1467-8659.2009.01398.x"]}, "10.1109/TVCG.2013.18": {"doi": "10.1109/TVCG.2013.18", "author": ["S. Shafii", "H. Obermaier", "R. Linn", "E. Koo", "M. Hlawitschka", "C. Garth", "B. Hamann", "K. I. Joy"], "title": "Visualization and Analysis of Vortex-Turbine Intersections in Wind Farms", "year": "2013", "abstract": "Characterizing the interplay between the vortices and forces acting on a wind turbine's blades in a qualitative and quantitative way holds the potential for significantly improving large wind turbine design. This paper introduces an integrated pipeline for highly effective wind and force field analysis and visualization. We extract vortices induced by a turbine's rotation in a wind field, and characterize vortices in conjunction with numerically simulated forces on the blade surfaces as these vortices strike another turbine's blades downstream. The scientifically relevant issue to be studied is the relationship between the extracted, approximate locations on the blades where vortices strike the blades and the forces that exist in those locations. This integrated approach is used to detect and analyze turbulent flow that causes local impact on the wind turbine blade structure. The results that we present are based on analyzing the wind and force field data sets generated by numerical simulations, and allow domain scientists to relate vortex-blade interactions with power output loss in turbines and turbine life expectancy. Our methods have the potential to improve turbine design to save costs related to turbine operation and maintenance.", "keywords": ["blades", "flow simulation", "flow visualisation", "numerical analysis", "turbulence", "vortices", "wind turbines", "vortex-turbine intersection visualization", "vortex-turbine intersection analysis", "wind farms", "wind field analysis", "force field analysis", "wind field visualization", "force field visualization", "turbine rotation", "numerical simulation", "blade surface", "turbulent flow", "wind turbine blade structure", "Blades", "Wind turbines", "Data visualization", "Feature extraction", "Force", "Geometry", "Flow visualization", "applications", "wind energy", "turbulence", "vortices"], "referenced_by": ["IKEY:8122685", "IKEY:8123181", "IKEY:7192723", "IKEY:7192672", "IKEY:8365977", "IKEY:7959130", "10.1017/jfm.2017.188", "10.1111/cgf.13532", "10.1177/1687814019825709", "10.3390/s20164556"], "referencing": ["IKEY:1532830", "IKEY:745296", "IKEY:689668", "IKEY:175773", "IKEY:4276078", "IKEY:346327", "IKEY:468404", "IKEY:346315", "IKEY:1532830", "IKEY:745296", "IKEY:689668", "IKEY:175773", "IKEY:4276078", "IKEY:346327", "IKEY:468404", "IKEY:346315", "IKEY:1532830", "IKEY:745296", "IKEY:689668", "IKEY:175773", "IKEY:4276078", "IKEY:346327", "IKEY:468404", "IKEY:346315", "10.1145/321062.321069", "10.1145/357306.357310", "10.1145/563858.563901", "10.1145/321062.321069", "10.1145/357306.357310", "10.1145/563858.563901", "10.1145/321062.321069", "10.1145/357306.357310", "10.1145/563858.563901", "10.1016/B978-012387582-2/50016-2", "10.1017/S0022112095000462", "10.1175/MWR2901.1", "10.1071/WF07120", "10.1071/WF07130", "10.2514/6.1983-1735", "10.2514/6.1995-1715", "10.1111/j.1467-8659.2008.01238.x", "10.1007/978-3-642-01106-1_30", "10.1111/j.1467-8659.2003.00723.x", "10.1016/B978-012387582-2/50016-2", "10.1017/S0022112095000462", "10.1175/MWR2901.1", "10.1071/WF07120", "10.1071/WF07130", "10.2514/6.1983-1735", "10.2514/6.1995-1715", "10.1111/j.1467-8659.2008.01238.x", "10.1007/978-3-642-01106-1_30", "10.1111/j.1467-8659.2003.00723.x", "10.1016/B978-012387582-2/50016-2", "10.1017/S0022112095000462", "10.1175/MWR2901.1", "10.1071/WF07120", "10.1071/WF07130", "10.2514/6.1983-1735", "10.2514/6.1995-1715", "10.1111/j.1467-8659.2008.01238.x", "10.1007/978-3-642-01106-1_30", "10.1111/j.1467-8659.2003.00723.x"]}, "10.1109/TVCG.2013.8": {"doi": "10.1109/TVCG.2013.8", "author": ["S. Patkar", "P. Chaudhuri"], "title": "Wetting of Porous Solids", "year": "2013", "abstract": "This paper presents a simple, three stage method to simulate the mechanics of wetting of porous solid objects, like sponges and cloth, when they interact with a fluid. In the first stage, we model the absorption of fluid by the object when it comes in contact with the fluid. In the second stage, we model the transport of absorbed fluid inside the object, due to diffusion, as a flow in a deforming, unstructured mesh. The fluid diffuses within the object depending on saturation of its various parts and other body forces. Finally, in the third stage, oversaturated parts of the object shed extra fluid by dripping. The simulation model is motivated by the physics of imbibition of fluids into porous solids in the presence of gravity. It is phenomenologically capable of simulating wicking and imbibition, dripping, surface flows over wet media, material weakening, and volume expansion due to wetting. The model is inherently mass conserving and works for both thin 2D objects like cloth and for 3D volumetric objects like sponges. It is also designed to be computationally efficient and can be easily added to existing cloth, soft body, and fluid simulation pipelines.", "keywords": ["diffusion", "flow through porous media", "mesh generation", "porous materials", "wetting", "wetting", "porous solids", "sponges", "cloth", "fluid", "transport modeling", "diffusion", "deforming unstructured mesh", "oversaturation", "dripping", "gravity", "surface flows", "material weakening", "mass conservation", "wicking", "Solids", "Solid modeling", "Computational modeling", "Mathematical model", "Gravity", "Absorption", "Deformable models", "Mechanics of wetting", "flow through porous solids", "Absorption", "Algorithms", "Computer Graphics", "Computer Simulation", "Diffusion", "Image Processing, Computer-Assisted", "Porosity", "Rheology", "Wettability"], "referenced_by": ["10.1145/3197517.3201392", "10.1145/3355089.3356532", "10.1002/cav.1788", "10.1111/cgf.12455", "10.1111/cgf.13214", "10.1371/journal.pone.0175695", "10.1111/cgf.14013", "10.1007/s00371-020-01963-w"], "referencing": ["IKEY:1500327", "IKEY:5246818", "IKEY:1500327", "IKEY:5246818", "IKEY:1500327", "IKEY:5246818", "10.1145/280814.280821", "10.1145/1360612.1360648", "10.1145/2037715.2037726", "10.1145/311535.311548", "10.1145/383259.383261", "10.1145/1531326.1531346", "10.1145/2019406.2019411", "10.1145/566570.566623", "10.1145/1559755.1559762", "10.1145/1275808.1276438", "10.1145/311535.311550", "10.1145/566570.566579", "10.1145/1276377.1276397", "10.1145/1360612.1360646", "10.1145/1778765.1778800", "10.1145/2019406.2019440", "10.1145/1015706.1015733", "10.1145/1073204.1073299", "10.1145/1179849.1179930", "10.1145/1276377.1276502", "10.1145/1073204.1073221", "10.1145/1073204.1073298", "10.1145/1276377.1276437", "10.1145/280814.280821", "10.1145/1360612.1360648", "10.1145/2037715.2037726", "10.1145/311535.311548", "10.1145/383259.383261", "10.1145/1531326.1531346", "10.1145/2019406.2019411", "10.1145/566570.566623", "10.1145/1559755.1559762", "10.1145/1275808.1276438", "10.1145/311535.311550", "10.1145/566570.566579", "10.1145/1276377.1276397", "10.1145/1360612.1360646", "10.1145/1778765.1778800", "10.1145/2019406.2019440", "10.1145/1015706.1015733", "10.1145/1073204.1073299", "10.1145/1179849.1179930", "10.1145/1276377.1276502", "10.1145/1073204.1073221", "10.1145/1073204.1073298", "10.1145/1276377.1276437", "10.1145/280814.280821", "10.1145/1360612.1360648", "10.1145/2037715.2037726", "10.1145/311535.311548", "10.1145/383259.383261", "10.1145/1531326.1531346", "10.1145/2019406.2019411", "10.1145/566570.566623", "10.1145/1559755.1559762", "10.1145/1275808.1276438", "10.1145/311535.311550", "10.1145/566570.566579", "10.1145/1276377.1276397", "10.1145/1360612.1360646", "10.1145/1778765.1778800", "10.1145/2019406.2019440", "10.1145/1015706.1015733", "10.1145/1073204.1073299", "10.1145/1179849.1179930", "10.1145/1276377.1276502", "10.1145/1073204.1073221", "10.1145/1073204.1073298", "10.1145/1276377.1276437", "10.1006/jcph.1994.1034", "10.1142/9789812564405", "10.1007/BF01908877", "10.1002/cav.18", "10.1016/S0266-352X(99)00026-9", "10.1006/jcph.2002.7189", "10.2136/vzj2004.1640", "10.1063/1.869901", "10.1063/1.870416", "10.1063/1.3068194", "10.1063/1.2000247", "10.1029/WR026i011p02797", "10.1103/PhysRevE.73.016307", "10.1080/10407780307318", "10.1016/S0169-7722(99)00019-4", "10.1006/jcph.1994.1034", "10.1142/9789812564405", "10.1007/BF01908877", "10.1002/cav.18", "10.1016/S0266-352X(99)00026-9", "10.1006/jcph.2002.7189", "10.2136/vzj2004.1640", "10.1063/1.869901", "10.1063/1.870416", "10.1063/1.3068194", "10.1063/1.2000247", "10.1029/WR026i011p02797", "10.1103/PhysRevE.73.016307", "10.1080/10407780307318", "10.1016/S0169-7722(99)00019-4", "10.1006/jcph.1994.1034", "10.1142/9789812564405", "10.1007/BF01908877", "10.1002/cav.18", "10.1016/S0266-352X(99)00026-9", "10.1006/jcph.2002.7189", "10.2136/vzj2004.1640", "10.1063/1.869901", "10.1063/1.870416", "10.1063/1.3068194", "10.1063/1.2000247", "10.1029/WR026i011p02797", "10.1103/PhysRevE.73.016307", "10.1080/10407780307318", "10.1016/S0169-7722(99)00019-4"]}}