{"10.1109/TVCG.2012.136": {"doi": "10.1109/TVCG.2012.136", "author": ["R. Wiemker", "T. Klinder", "M. Bergtholdt", "K. Meetz", "I. C. Carlsen", "T. B\u00fclow"], "title": "A Radial Structure Tensor and Its Use for Shape-Encoding Medical Visualization of Tubular and Nodular Structures", "year": "2013", "abstract": "The concept of curvature and shape-based rendering is beneficial for medical visualization of CT and MRI image volumes. Color-coding of local shape properties derived from the analysis of the local Hessian can implicitly highlight tubular structures such as vessels and airways, and guide the attention to potentially malignant nodular structures such as tumors, enlarged lymph nodes, or aneurysms. For some clinical applications, however, the evaluation of the Hessian matrix does not yield satisfactory renderings, in particular for hollow structures such as airways, and densely embedded low contrast structures such as lymph nodes. Therefore, as a complement to Hessian-based shape-encoding rendering, this paper introduces a combination of an efficient sparse radial gradient sampling scheme in conjunction with a novel representation, the radial structure tensor (RST). As an extension of the well-known general structure tensor, which has only positive definite eigenvalues, the radial structure tensor correlates position and direction of the gradient vectors in a local neighborhood, and thus yields positive and negative eigenvalues which can be used to discriminate between different shapes. As Hessian-based rendering, also RST-based rendering is ideally suited for GPU implementation. Feedback from clinicians indicates that shape-encoding rendering can be an effective image navigation tool to aid diagnostic workflow and quality assurance.", "keywords": ["biomedical MRI", "computerised tomography", "data visualisation", "gradient methods", "Hessian matrices", "medical image processing", "rendering (computer graphics)", "tensors", "radial structure tensor", "shape encoding medical visualization", "nodular structures", "tubular structures", "shape based rendering", "curvature based rendering", "MRI image volumes", "CT image volumes", "color coding", "shape properties", "Hessian matrix", "sparse radial gradient sampling", "RST", "positive definite eigenvalues", "GPU implementation", "shape encoding rendering", "Rendering (computer graphics)", "Tensile stress", "Eigenvalues and eigenfunctions", "Image color analysis", "Biomedical imaging", "Curvature-based rendering", "shape-based rendering", "vessels", "airways", "lymph nodes", "tumors", "Algorithms", "Computer Graphics", "Humans", "Image Enhancement", "Image Interpretation, Computer-Assisted", "Imaging, Three-Dimensional", "Magnetic Resonance Imaging", "Reproducibility of Results", "Sensitivity and Specificity", "Tomography, X-Ray Computed", "User-Computer Interface"], "referenced_by": ["IKEY:7446363", "IKEY:7127031", "IKEY:8606958", "10.1016/j.media.2015.07.001", "10.1117/12.2043349", "10.1117/12.2254782", "10.1117/12.2216747", "10.1117/12.2214925", "10.1117/12.2081917", "10.1117/12.2081147", "10.1117/1.JMI.4.4.044502", "10.1016/j.ejrad.2019.02.010", "10.1117/12.2521646", "10.1016/j.compmedimag.2019.06.001", "10.1007/978-981-13-9184-2_42", "10.1080/15732479.2019.1655068", "10.1007/978-3-030-32689-0_11", "10.1007/978-981-15-7961-5_46", "10.1016/j.ejrad.2020.109410", "10.1117/1.JEI.29.6.063008"], "referencing": ["IKEY:1413497", "IKEY:4658181", "IKEY:1703376", "IKEY:4906857", "IKEY:5613470", "IKEY:729588", "IKEY:1343846", "IKEY:964515", "IKEY:856997", "IKEY:1250414", "IKEY:1413497", "IKEY:4658181", "IKEY:1703376", "IKEY:4906857", "IKEY:5613470", "IKEY:729588", "IKEY:1343846", "IKEY:964515", "IKEY:856997", "IKEY:1250414", "IKEY:1413497", "IKEY:4658181", "IKEY:1703376", "IKEY:4906857", "IKEY:5613470", "IKEY:729588", "IKEY:1343846", "IKEY:964515", "IKEY:856997", "IKEY:1250414", "10.1007/978-3-540-73273-0_12", "10.1007/11499145_49", "10.1016/j.media.2008.05.005", "10.1080/757582976", "10.1016/j.imavis.2005.09.010", "10.1016/0734-189X(86)90223-9", "10.1007/978-3-540-88378-4_13", "10.1016/S0006-8993(97)00635-5", "10.1007/3-540-31272-2_7", "10.1117/12.843797", "10.1148/rg.321105076", "10.1148/radiol.2222010506", "10.1016/j.media.2010.08.003", "10.1118/1.1581411", "10.1007/BFb0029242", "10.1006/cviu.2000.0866", "10.1002/(SICI)1522-2594(199909)42:3&lt;515::AID-MRM14&gt;3.3.CO;2-H", "10.1148/radiol.2432052052", "10.1259/bjr/30281702", "10.1007/11566465_85", "10.1016/j.lungcan.2010.10.025", "10.1378/chest.08-0684", "10.1259/bjr/82933343", "10.1007/978-3-540-73273-0_12", "10.1007/11499145_49", "10.1016/j.media.2008.05.005", "10.1080/757582976", "10.1016/j.imavis.2005.09.010", "10.1016/0734-189X(86)90223-9", "10.1007/978-3-540-88378-4_13", "10.1016/S0006-8993(97)00635-5", "10.1007/3-540-31272-2_7", "10.1117/12.843797", "10.1148/rg.321105076", "10.1148/radiol.2222010506", "10.1016/j.media.2010.08.003", "10.1118/1.1581411", "10.1007/BFb0029242", "10.1006/cviu.2000.0866", "10.1002/(SICI)1522-2594(199909)42:3&lt;515::AID-MRM14&gt;3.3.CO;2-H", "10.1148/radiol.2432052052", "10.1259/bjr/30281702", "10.1007/11566465_85", "10.1016/j.lungcan.2010.10.025", "10.1378/chest.08-0684", "10.1259/bjr/82933343", "10.1007/978-3-540-73273-0_12", "10.1007/11499145_49", "10.1016/j.media.2008.05.005", "10.1080/757582976", "10.1016/j.imavis.2005.09.010", "10.1016/0734-189X(86)90223-9", "10.1007/978-3-540-88378-4_13", "10.1016/S0006-8993(97)00635-5", "10.1007/3-540-31272-2_7", "10.1117/12.843797", "10.1148/rg.321105076", "10.1148/radiol.2222010506", "10.1016/j.media.2010.08.003", "10.1118/1.1581411", "10.1007/BFb0029242", "10.1006/cviu.2000.0866", "10.1002/(SICI)1522-2594(199909)42:3&lt;515::AID-MRM14&gt;3.3.CO;2-H", "10.1148/radiol.2432052052", "10.1259/bjr/30281702", "10.1007/11566465_85", "10.1016/j.lungcan.2010.10.025", "10.1378/chest.08-0684", "10.1259/bjr/82933343"]}, "10.1109/TVCG.2012.133": {"doi": "10.1109/TVCG.2012.133", "author": ["K. Moreland"], "title": "A Survey of Visualization Pipelines", "year": "2013", "abstract": "The most common abstraction used by visualization libraries and applications today is what is known as the visualization pipeline. The visualization pipeline provides a mechanism to encapsulate algorithms and then couple them together in a variety of ways. The visualization pipeline has been in existence for over 20 years, and over this time many variations and improvements have been proposed. This paper provides a literature review of the most prevalent features of visualization pipelines and some of the most recent research directions.", "keywords": ["data visualisation", "libraries", "visualization pipelines", "visualization libraries", "abstraction", "Data visualization", "Pipelilnes", "Distributed control", "Data models", "Rendering (computer graphics)", "Centralized control", "Visualization pipelines", "dataflow networks", "event driven", "push model", "demand driven", "pull model", "central control", "distributed control", "pipeline executive", "out-of-core streaming", "temporal visualization", "pipeline contracts", "prioritized streaming", "query-driven visualization", "parallel visualization", "task parallelism", "pipeline parallelism", "data parallelism", "rendering", "hybrid parallel", "provenance", "scheduling", "in situ visualization", "functional field model", "MapReduce", "domain specific languages", "Algorithms", "Computer Graphics", "Image Enhancement", "Image Interpretation, Computer-Assisted", "Imaging, Three-Dimensional", "Information Storage and Retrieval", "Reproducibility of Results", "Sensitivity and Specificity", "Software", "User-Computer Interface"], "referenced_by": ["IKEY:8029621", "IKEY:7391834", "IKEY:6676571", "IKEY:7465249", "IKEY:6787134", "IKEY:6676506", "IKEY:7429514", "IKEY:6717981", "IKEY:7172541", "IKEY:7368928", "IKEY:8017627", "IKEY:7294442", "IKEY:7272576", "IKEY:8440821", "IKEY:8730513", "10.1145/2659021.2659048", "10.1007/978-3-319-25117-2_7", "10.1007/s11390-016-1663-1", "10.1007/s12650-015-0335-5", "10.1016/j.future.2014.11.017", "10.1016/j.gmod.2016.03.005", "10.1016/j.jvlc.2016.10.001", "10.1111/cgf.12605", "10.1142/S1793962318400044", "10.1177/1473871613510429", "10.15748/jasse.2.76", "10.2200/S00651ED1V01Y201506VIS003", "10.3390/ijgi3041445", "10.1007/978-981-13-1396-7_4", "10.9728/dcs.2018.19.8.1463", "10.5194/gmd-12-233-2019", "10.1007/978-3-642-36113-5_16", "10.1177/1473871619881114", "10.1007/978-3-030-41050-6_7", "10.1016/j.cosrev.2020.100245", "10.1016/j.future.2020.06.056"], "referencing": ["10.1145/1838544.1838545", "10.1145/1654059.1654076", "10.1145/2110205.2110207", "10.1145/1327452.1327492", "10.1145/1376616.1376726", "10.1145/1559845.1559962", "10.1145/1851476.1851597", "10.1145/2159430.2159432", "10.1145/43965.43966", "10.1145/378456.378494", "10.1145/37402.37422", "10.1145/384192.384193", "10.1145/1670243.1670245", "10.1145/224170.224354", "10.1145/142920.134087", "10.1145/97880.97910", "10.1145/964965.808602", "10.1145/325334.325247", "10.1145/327164.327331", "10.1145/204362.204365", "10.1145/1838544.1838545", "10.1145/1654059.1654076", "10.1145/2110205.2110207", "10.1145/1327452.1327492", "10.1145/1376616.1376726", "10.1145/1559845.1559962", "10.1145/1851476.1851597", "10.1145/2159430.2159432", "10.1145/43965.43966", "10.1145/378456.378494", "10.1145/37402.37422", "10.1145/384192.384193", "10.1145/1670243.1670245", "10.1145/224170.224354", "10.1145/142920.134087", "10.1145/97880.97910", "10.1145/964965.808602", "10.1145/325334.325247", "10.1145/327164.327331", "10.1145/204362.204365", "10.1145/1838544.1838545", "10.1145/1654059.1654076", "10.1145/2110205.2110207", "10.1145/1327452.1327492", "10.1145/1376616.1376726", "10.1145/1559845.1559962", "10.1145/1851476.1851597", "10.1145/2159430.2159432", "10.1145/43965.43966", "10.1145/378456.378494", "10.1145/37402.37422", "10.1145/384192.384193", "10.1145/1670243.1670245", "10.1145/224170.224354", "10.1145/142920.134087", "10.1145/97880.97910", "10.1145/964965.808602", "10.1145/325334.325247", "10.1145/327164.327331", "10.1145/204362.204365", "10.1016/0021-9991(89)90035-1", "10.1117/12.706325", "10.1007/BFb0095358", "10.1007/978-3-540-69303-1_10", "10.1007/978-3-540-89965-5_27", "10.1088/1742-6596/78/1/012012", "10.1088/1742-6596/125/1/012099", "10.1111/j.1467-8659.2009.01704.x", "10.1016/j.parco.2007.09.001", "10.1088/1742-6596/180/1/012053", "10.1117/12.704533", "10.1016/0167-8655(94)90125-2", "10.1007/s10278-004-1014-6", "10.1017/S1431927608083621", "10.1016/0021-9991(89)90035-1", "10.1117/12.706325", "10.1007/BFb0095358", "10.1007/978-3-540-69303-1_10", "10.1007/978-3-540-89965-5_27", "10.1088/1742-6596/78/1/012012", "10.1088/1742-6596/125/1/012099", "10.1111/j.1467-8659.2009.01704.x", "10.1016/j.parco.2007.09.001", "10.1088/1742-6596/180/1/012053", "10.1117/12.704533", "10.1016/0167-8655(94)90125-2", "10.1007/s10278-004-1014-6", "10.1017/S1431927608083621", "10.1016/0021-9991(89)90035-1", "10.1117/12.706325", "10.1007/BFb0095358", "10.1007/978-3-540-69303-1_10", "10.1007/978-3-540-89965-5_27", "10.1088/1742-6596/78/1/012012", "10.1088/1742-6596/125/1/012099", "10.1111/j.1467-8659.2009.01704.x", "10.1016/j.parco.2007.09.001", "10.1088/1742-6596/180/1/012053", "10.1117/12.704533", "10.1016/0167-8655(94)90125-2", "10.1007/s10278-004-1014-6", "10.1017/S1431927608083621"]}, "10.1109/TVCG.2012.131": {"doi": "10.1109/TVCG.2012.131", "author": ["M. Uffinger", "F. Sadlo", "T. Ertl"], "title": "A Time-Dependent Vector Field Topology Based on Streak Surfaces", "year": "2013", "abstract": "It was shown recently how the 2D vector field topology concept, directly applicable to stationary vector fields only, can be generalized to time-dependent vector fields by replacing the role of stream lines by streak lines [1]. The present paper extends this concept to 3D vector fields. In traditional 3D vector field topology separatrices can be obtained by integrating stream lines from 0D seeds corresponding to critical points. We show that in our new concept, in contrast, 1D seeding constructs are required for computing streak-based separatrices. In analogy to the 2D generalization we show that invariant manifolds can be obtained by seeding streak surfaces along distinguished path surfaces emanating from intersection curves between codimension-1 ridges in the forward and reverse finite-time Lyapunov exponent (FTLE) fields. These path surfaces represent a time-dependent generalization of critical points and convey further structure in time-dependent topology of vector fields. Compared to the traditional approach based on FTLE ridges, the resulting streak manifolds ease the analysis of Lagrangian coherent structures (LCS) with respect to visual quality and computational cost, especially when time series of LCS are computed. We exemplify validity and utility of the new approach using both synthetic examples and computational fluid dynamics results.", "keywords": ["data visualisation", "time series", "time-dependent vector field topology", "streak surfaces", "2D vector field topology concept", "stationary vector fields", "streak lines", "3D vector field topology separatrices", "0D seeds", "critical points", "1D seeding", "2D generalization", "intersection curves", "codimension-1 ridges", "forward and reverse finite-time Lyapunov exponent fields", "FTLE ridges", "streak manifolds", "Lagrangian coherent structures", "LCS", "visual quality", "computational cost", "time series", "computational fluid dynamics", "CFD", "Vectors", "Manifolds", "Topology", "Three dimensional displays", "Eigenvalues and eigenfunctions", "Trajectory", "Surface reconstruction", "Vector field topology", "Lagrangian coherent structures", "streak lines", "time-dependent vector fields", "Algorithms", "Computer Graphics", "Image Enhancement", "Image Interpretation, Computer-Assisted", "Imaging, Three-Dimensional", "Reproducibility of Results", "Rheology", "Sensitivity and Specificity", "User-Computer Interface"], "referenced_by": ["IKEY:7938244", "IKEY:7973183", "IKEY:6875962", "IKEY:7305807", "IKEY:7539598", "IKEY:7539608", "IKEY:8781578", "IKEY:9086231", "10.1007/978-3-319-44684-4_15", "10.1007/s12650-015-0284-z", "10.1111/cgf.12269", "10.1111/cgf.12659", "10.1111/cgf.12885", "10.1111/cgf.12914", "10.1111/cgf.12933", "10.1111/cgf.13421", "10.1007/978-3-319-04099-8_14", "10.1007/978-3-030-03801-4_32", "10.1007/978-3-642-38241-3_10", "10.1007/978-3-662-44900-4_10", "10.1111/cgf.14093", "10.1016/j.cag.2020.10.001", "10.1111/cgf.14183"], "referencing": ["IKEY:4376174", "IKEY:928168", "IKEY:35197", "IKEY:79452", "IKEY:175773", "IKEY:809896", "IKEY:745297", "IKEY:1372213", "IKEY:5613499", "IKEY:4658156", "IKEY:5290738", "IKEY:5290737", "IKEY:4376209", "IKEY:5613462", "IKEY:4376175", "IKEY:5611509", "IKEY:5613496", "IKEY:4376174", "IKEY:928168", "IKEY:35197", "IKEY:79452", "IKEY:175773", "IKEY:809896", "IKEY:745297", "IKEY:1372213", "IKEY:5613499", "IKEY:4658156", "IKEY:5290738", "IKEY:5290737", "IKEY:4376209", "IKEY:5613462", "IKEY:4376175", "IKEY:5611509", "IKEY:5613496", "IKEY:4376174", "IKEY:928168", "IKEY:35197", "IKEY:79452", "IKEY:175773", "IKEY:809896", "IKEY:745297", "IKEY:1372213", "IKEY:5613499", "IKEY:4658156", "IKEY:5290738", "IKEY:5290737", "IKEY:4376209", "IKEY:5613462", "IKEY:4376175", "IKEY:5611509", "IKEY:5613496", "10.1111/j.1467-8659.2009.01546.x", "10.1016/S0167-2789(00)00199-8", "10.1016/j.physd.2005.10.007", "10.1007/978-3-642-23175-9_18", "10.1007/978-3-540-88606-8_3", "10.1111/j.1467-8659.2011.01925.x", "10.1111/j.1467-8659.2009.01686.x", "10.1063/1.166479", "10.1007/978-94-015-8765-5", "10.1111/j.1467-8659.2009.01546.x", "10.1016/S0167-2789(00)00199-8", "10.1016/j.physd.2005.10.007", "10.1007/978-3-642-23175-9_18", "10.1007/978-3-540-88606-8_3", "10.1111/j.1467-8659.2011.01925.x", "10.1111/j.1467-8659.2009.01686.x", "10.1063/1.166479", "10.1007/978-94-015-8765-5", "10.1111/j.1467-8659.2009.01546.x", "10.1016/S0167-2789(00)00199-8", "10.1016/j.physd.2005.10.007", "10.1007/978-3-642-23175-9_18", "10.1007/978-3-540-88606-8_3", "10.1111/j.1467-8659.2011.01925.x", "10.1111/j.1467-8659.2009.01686.x", "10.1063/1.166479", "10.1007/978-94-015-8765-5"]}, "10.1109/TVCG.2012.143": {"doi": "10.1109/TVCG.2012.143", "author": ["J. Tao", "J. Ma", "C. Wang", "C. Shene"], "title": "A Unified Approach to Streamline Selection and Viewpoint Selection for 3D Flow Visualization", "year": "2013", "abstract": "We treat streamline selection and viewpoint selection as symmetric problems which are formulated into a unified information-theoretic framework. This is achieved by building two interrelated information channels between a pool of candidate streamlines and a set of sample viewpoints. We define the streamline information to select best streamlines and in a similar manner, define the viewpoint information to select best viewpoints. Furthermore, we propose solutions to streamline clustering and viewpoint partitioning based on the representativeness of streamlines and viewpoints, respectively. Finally, we define a camera path that passes through all selected viewpoints for automatic flow field exploration. We demonstrate the robustness of our approach by showing experimental results with different flow data sets, and conducting rigorous comparisons between our algorithm and other seed placement or streamline selection algorithms based on information theory.", "keywords": ["data visualisation", "information theory", "pattern clustering", "viewpoint selection", "3D flow visualization", "symmetric problems", "unified information-theoretic framework", "interrelated information channels", "sample viewpoints", "streamline clustering", "viewpoint partitioning", "streamlines representativeness", "camera path", "automatic flow field exploration", "flow data sets", "streamline selection algorithms", "Vectors", "Shape", "Mutual information", "Silicon", "Probability distribution", "Cameras", "Data visualization", "Flow visualization", "information channel", "streamline selection", "viewpoint selection", "camera path", "Algorithms", "Computer Graphics", "Image Enhancement", "Image Interpretation, Computer-Assisted", "Imaging, Three-Dimensional", "Reproducibility of Results", "Rheology", "Sensitivity and Specificity", "User-Computer Interface"], "referenced_by": ["IKEY:8258329", "IKEY:6934128", "IKEY:8231856", "IKEY:6787131", "IKEY:6787133", "IKEY:7013022", "IKEY:7379300", "IKEY:7844406", "IKEY:7572970", "IKEY:6559983", "IKEY:7117453", "IKEY:7470264", "IKEY:7063265", "IKEY:8365995", "IKEY:8447553", "IKEY:8739144", "IKEY:8532319", "IKEY:9122356", "IKEY:8713907", "10.1145/2461912.2461930", "10.1002/cav.1664", "10.1007/s12650-016-0358-6", "10.1016/B978-0-12-415873-3.00035-3", "10.1016/j.jvlc.2017.04.001", "10.1016/j.parco.2015.10.005", "10.1111/cgf.12335", "10.1111/cgf.13115", "10.1111/cgf.13528", "10.4028/www.scientific.net/AMM.347-350.2197", "10.1007/978-981-287-540-2_7", "10.1007/978-3-319-21963-9_27", "10.1111/cgf.12112", "10.3390/e21070699", "10.1007/s12650-019-00592-3", "10.1186/s42492-020-00056-8", "10.1016/j.visinf.2020.09.001", "10.1007/978-3-030-61864-3_26"], "referencing": ["IKEY:791227", "IKEY:1532833", "IKEY:5613460", "IKEY:4376173", "IKEY:4015471", "IKEY:5742376", "IKEY:4475462", "IKEY:5613500", "IKEY:1532832", "IKEY:1532779", "IKEY:4906832", "IKEY:1532834", "IKEY:885690", "IKEY:4015449", "IKEY:810066", "IKEY:609299", "IKEY:5613461", "IKEY:1532831", "IKEY:791227", "IKEY:1532833", "IKEY:5613460", "IKEY:4376173", "IKEY:4015471", "IKEY:5742376", "IKEY:4475462", "IKEY:5613500", "IKEY:1532832", "IKEY:1532779", "IKEY:4906832", "IKEY:1532834", "IKEY:885690", "IKEY:4015449", "IKEY:810066", "IKEY:609299", "IKEY:5613461", "IKEY:1532831", "IKEY:791227", "IKEY:1532833", "IKEY:5613460", "IKEY:4376173", "IKEY:4015471", "IKEY:5742376", "IKEY:4475462", "IKEY:5613500", "IKEY:1532832", "IKEY:1532779", "IKEY:4906832", "IKEY:1532834", "IKEY:885690", "IKEY:4015449", "IKEY:810066", "IKEY:609299", "IKEY:5613461", "IKEY:1532831", "10.1145/1462055.1462056", "10.1145/237170.237259", "10.1145/237170.237285", "10.1145/1462055.1462056", "10.1145/237170.237259", "10.1145/237170.237285", "10.1145/1462055.1462056", "10.1145/237170.237259", "10.1145/237170.237285", "10.1111/1467-8659.00447", "10.1111/j.1467-8659.2011.01927.x", "10.1007/978-3-7091-6876-9_5", "10.1214/aoms/1177729694", "10.1029/2004EO400002", "10.1111/j.1467-8659.2010.01650.x", "10.1016/j.cag.2010.01.006", "10.1111/j.1467-8659.2009.01352.x", "10.3390/e13010254", "10.1111/1467-8659.00447", "10.1111/j.1467-8659.2011.01927.x", "10.1007/978-3-7091-6876-9_5", "10.1214/aoms/1177729694", "10.1029/2004EO400002", "10.1111/j.1467-8659.2010.01650.x", "10.1016/j.cag.2010.01.006", "10.1111/j.1467-8659.2009.01352.x", "10.3390/e13010254", "10.1111/1467-8659.00447", "10.1111/j.1467-8659.2011.01927.x", "10.1007/978-3-7091-6876-9_5", "10.1214/aoms/1177729694", "10.1029/2004EO400002", "10.1111/j.1467-8659.2010.01650.x", "10.1016/j.cag.2010.01.006", "10.1111/j.1467-8659.2009.01352.x", "10.3390/e13010254"]}, "10.1109/TVCG.2012.135": {"doi": "10.1109/TVCG.2012.135", "author": ["P. Harish", "P. J. Narayanan"], "title": "Designing Perspectively Correct Multiplanar Displays", "year": "2013", "abstract": "Displays remain flat and passive amidst the many changes in their fundamental technologies. One natural step ahead is to create displays that merge seamlessly in shape and appearance with one's natural surroundings. In this paper, we present a system to design, render to, and build view-dependent multiplanar displays of arbitrary piecewise-planar shapes, built using polygonal facets. Our system provides high quality, interactive rendering of 3D environments to a head-tracked viewer on arbitrary multiplanar displays. We develop a novel rendering scheme that produces exact image and depth map at each facet, producing artifact-free images on and across facet boundaries. The system scales to a large number of display facets by rendering all facets in a single pass of rasterization. This is achieved using a parallel, perframe, view-dependent binning and prewarping of scene triangles. The display is driven using one or more target quilt images into which facet pixels are packed. Our method places no constraints on the scene or the display and allows for fully dynamic scenes to be rendered interactively at high resolutions. The steps of our system are implemented efficiently on commodity GPUs. We present a few prototype displays to establish the scalability of our system on different display shapes, form factors, and complexity: from a cube made out of LCD panels to spherical/cylindrical projected setups to arbitrary complex shapes in simulation. Performance of our system is demonstrated for both rendering quality and speed, for increasing scene and display facet sizes. A subjective user study is also presented to evaluate the user experience using a walk-around display compared to a flat panel for a game-like setting.", "keywords": ["display devices", "rendering (computer graphics)", "view-dependent multiplanar displays", "arbitrary piecewise-planar shapes", "polygonal facets", "interactive rendering", "3D environments", "head-tracked viewer", "image map", "depth map", "artifact-free images", "facet boundaries", "display facets", "rasterization", "scene triangles", "view-dependent binning", "prewarping", "facet pixels", "dynamic scenes", "commodity GPU", "prototype displays", "display shapes", "form factors", "LCD panels", "spherical-cylindrical projected setups", "arbitrary complex shapes", "rendering quality", "rendering speed", "subjective user study", "user experience", "walk-around display", "flat panel display", "game-like setting", "Rendering (computer graphics)", "Three dimensional displays", "Shape", "Cameras", "Pipelines", "Head", "Nonrectangular displays", "fish tank virtual reality", "arbitrary shaped displays", "3D visualization", "view-dependent rendering", "parallel culling", "user interaction", "Algorithms", "Computer Graphics", "Image Enhancement", "Image Interpretation, Computer-Assisted", "Imaging, Three-Dimensional", "Numerical Analysis, Computer-Assisted", "Signal Processing, Computer-Assisted", "User-Computer Interface"], "referenced_by": ["IKEY:6671779", "IKEY:7892378", "10.1007/s11042-019-08324-3", "10.1080/10447318.2019.1699746"], "referencing": ["IKEY:6162880", "IKEY:1544657", "IKEY:1315159", "IKEY:840488", "IKEY:4276073", "IKEY:6060818", "IKEY:1467467", "IKEY:6162880", "IKEY:1544657", "IKEY:1315159", "IKEY:840488", "IKEY:4276073", "IKEY:6060818", "IKEY:1467467", "IKEY:6162880", "IKEY:1544657", "IKEY:1315159", "IKEY:840488", "IKEY:4276073", "IKEY:6060818", "IKEY:1467467", "10.1145/1283900.1283904", "10.1145/166117.166134", "10.1145/778712.778734", "10.1145/1179849.1180055", "10.1145/1753326.1753535", "10.1145/142920.134039", "10.1145/1670252.1670269", "10.1145/1572741.1572755", "10.1145/502348.502354", "10.1145/365024.365114", "10.1145/1449715.1449729", "10.1145/383251.383255", "10.1145/1283900.1283904", "10.1145/166117.166134", "10.1145/778712.778734", "10.1145/1179849.1180055", "10.1145/1753326.1753535", "10.1145/142920.134039", "10.1145/1670252.1670269", "10.1145/1572741.1572755", "10.1145/502348.502354", "10.1145/365024.365114", "10.1145/1449715.1449729", "10.1145/383251.383255", "10.1145/1283900.1283904", "10.1145/166117.166134", "10.1145/778712.778734", "10.1145/1179849.1180055", "10.1145/1753326.1753535", "10.1145/142920.134039", "10.1145/1670252.1670269", "10.1145/1572741.1572755", "10.1145/502348.502354", "10.1145/365024.365114", "10.1145/1449715.1449729", "10.1145/383251.383255", "10.1016/j.intcom.2006.08.002", "10.1023/B:VISI.0000019685.36452.55", "10.1111/j.1467-8659.2011.02035.x", "10.1017/CBO9780511811685", "10.1080/10867651.1997.10487472", "10.1016/j.intcom.2006.08.002", "10.1023/B:VISI.0000019685.36452.55", "10.1111/j.1467-8659.2011.02035.x", "10.1017/CBO9780511811685", "10.1080/10867651.1997.10487472", "10.1016/j.intcom.2006.08.002", "10.1023/B:VISI.0000019685.36452.55", "10.1111/j.1467-8659.2011.02035.x", "10.1017/CBO9780511811685", "10.1080/10867651.1997.10487472"]}, "10.1109/TVCG.2012.66": {"doi": "10.1109/TVCG.2012.66", "author": ["J. Zhang", "G. Baciu", "D. Zheng", "C. Liang", "G. Li", "J. Hu"], "title": "IDSS: A Novel Representation for Woven Fabrics", "year": "2013", "abstract": "The appearance of woven fabrics is intrinsically determined by the geometric details of their meso/micro scale structure. In this paper, we propose a multiscale representation and tessellation approach for woven fabrics. We extend the Displaced Subdivision Surface (DSS) to a representation named Interlaced/Intertwisted Displacement Subdivision Surface (IDSS). IDSS maps the geometric detail, scale by scale, onto a ternary interpolatory subdivision surface that is approximated by Bezier patches. This approach is designed for woven fabric rendering on DX11 GPUs. We introduce the Woven Patch, a structure based on DirectX's new primitive, patch, to describe an area of a woven fabric so that it can be easily implemented in the graphics pipeline using a hull shader, a tessellator and a domain shader. We can render a woven piece of fabric at 25 frames per second on a low-performance NVIDIA 8400 MG mobile GPU. This allows for large-scale representations of woven fabrics that maintain the geometric variances of real yarn and fiber.", "keywords": ["fabrics", "geometry", "graphics processing units", "production engineering computing", "woven fabrics", "geometric details", "meso-micro scale structure", "multiscale representation", "tessellation approach", "interlaced-intertwisted displacement subdivision surface", "IDSS maps", "ternary interpolatory subdivision surface", "Bezier patches", "DX11 GPU", "woven patch", "DirectX", "graphics pipeline", "hull shader", "domain shader", "low-performance NVIDIA 8400 MG mobile GPU", "real yarn", "real fiber", "Weaving", "Fabrics", "Yarn", "Equations", "Approximation methods", "Mathematical model", "Geometry", "Woven fabric", "subdivision surface", "interlaced displacement", "intertwisted displacement", "tessellation", "GPU", "Algorithms", "Computer Graphics", "Image Enhancement", "Image Interpretation, Computer-Assisted", "Imaging, Three-Dimensional", "Pattern Recognition, Automated", "Reproducibility of Results", "Sensitivity and Specificity", "Textiles", "User-Computer Interface"], "referenced_by": ["10.1145/2818648", "10.1145/3306346.3323031", "10.1016/B978-0-08-101217-8.00002-6", "10.1016/j.cam.2017.04.051", "10.1177/0040517516673331", "10.5772/67736", "10.1080/00405000.2018.1509503", "10.1631/FITEE.1800693", "10.1080/00405000.2019.1565619"], "referencing": ["IKEY:5477421", "IKEY:6076004", "IKEY:1407865", "IKEY:1333663", "IKEY:5477421", "IKEY:6076004", "IKEY:1407865", "IKEY:1333663", "IKEY:5477421", "IKEY:6076004", "IKEY:1407865", "IKEY:1333663", "10.1145/1330511.1330519", "10.1145/383259.383303", "10.1145/1008653.1008663", "10.1145/360349.360353", "10.1145/800248.507101", "10.1145/964965.808602", "10.1145/1186562.1015773", "10.1145/1186822.1073239", "10.1145/882262.882272", "10.1145/1321261.1321299", "10.1145/1071866.1071882", "10.1145/1409060.1409094", "10.1145/344779.344829", "10.1145/1141911.1141947", "10.1145/1330511.1330519", "10.1145/383259.383303", "10.1145/1008653.1008663", "10.1145/360349.360353", "10.1145/800248.507101", "10.1145/964965.808602", "10.1145/1186562.1015773", "10.1145/1186822.1073239", "10.1145/882262.882272", "10.1145/1321261.1321299", "10.1145/1071866.1071882", "10.1145/1409060.1409094", "10.1145/344779.344829", "10.1145/1141911.1141947", "10.1145/1330511.1330519", "10.1145/383259.383303", "10.1145/1008653.1008663", "10.1145/360349.360353", "10.1145/800248.507101", "10.1145/964965.808602", "10.1145/1186562.1015773", "10.1145/1186822.1073239", "10.1145/882262.882272", "10.1145/1321261.1321299", "10.1145/1071866.1071882", "10.1145/1409060.1409094", "10.1145/344779.344829", "10.1145/1141911.1141947", "10.1016/0010-4485(78)90111-2", "10.1016/0010-4485(78)90110-0", "10.1016/S0167-8396(01)00084-X", "10.1016/j.cagd.2005.05.001", "10.1016/j.cagd.2007.02.001", "10.1080/00405000701757958", "10.1111/j.1467-8659.2009.01438.x", "10.1016/j.cag.2007.06.002", "10.1016/j.cag.2003.10.006", "10.1111/j.1467-8659.2007.01040.x", "10.1016/0010-4485(78)90111-2", "10.1016/0010-4485(78)90110-0", "10.1016/S0167-8396(01)00084-X", "10.1016/j.cagd.2005.05.001", "10.1016/j.cagd.2007.02.001", "10.1080/00405000701757958", "10.1111/j.1467-8659.2009.01438.x", "10.1016/j.cag.2007.06.002", "10.1016/j.cag.2003.10.006", "10.1111/j.1467-8659.2007.01040.x", "10.1016/0010-4485(78)90111-2", "10.1016/0010-4485(78)90110-0", "10.1016/S0167-8396(01)00084-X", "10.1016/j.cagd.2005.05.001", "10.1016/j.cagd.2007.02.001", "10.1080/00405000701757958", "10.1111/j.1467-8659.2009.01438.x", "10.1016/j.cag.2007.06.002", "10.1016/j.cag.2003.10.006", "10.1111/j.1467-8659.2007.01040.x"]}, "10.1109/TVCG.2012.142": {"doi": "10.1109/TVCG.2012.142", "author": ["S. Eichelbaum", "M. Hlawitschka", "G. Scheuermann"], "title": "LineAO\u2014Improved Three-Dimensional Line Rendering", "year": "2013", "abstract": "Rendering large numbers of dense line bundles in three dimensions is a common need for many visualization techniques, including streamlines and fiber tractography. Unfortunately, depiction of spatial relations inside these line bundles is often difficult but critical for understanding the represented structures. Many approaches evolved for solving this problem by providing special illumination models or tube-like renderings. Although these methods improve spatial perception of individual lines or related sets of lines, they do not solve the problem for complex spatial relations between dense bundles of lines. In this paper, we present a novel approach that improves spatial and structural perception of line renderings by providing a novel ambient occlusion approach suited for line rendering in real time.", "keywords": ["data visualisation", "rendering (computer graphics)", "LineAO", "three-dimensional line rendering improvement", "dense line bundles", "visualization techniques", "streamlines", "fiber tractography", "illumination models", "tube-like renderings", "spatial perception improvement", "complex spatial relations", "structural perception", "ambient occlusion approach", "Rendering (computer graphics)", "Lighting", "Real time systems", "Spatial resolution", "Data visualization", "Equations", "Vectors", "GPU", "ambient occlusion", "illumination", "diffusion tensor data", "fiber tracking", "streamline visualization", "Algorithms", "Computer Graphics", "Computer Systems", "Image Enhancement", "Image Interpretation, Computer-Assisted", "Imaging, Three-Dimensional", "Numerical Analysis, Computer-Assisted", "Signal Processing, Computer-Assisted", "User-Computer Interface"], "referenced_by": ["IKEY:7156357", "IKEY:8031577", "IKEY:7429512", "IKEY:7390081", "IKEY:6650534", "IKEY:7294450", "IKEY:8807369", "IKEY:8727493", "10.1145/2461912.2461930", "10.1007/s40708-017-0071-9", "10.1016/j.neuroimage.2013.04.111", "10.1016/j.neuroimage.2014.04.085", "10.1111/cgf.12627", "10.1111/cgf.12927", "10.1371/journal.pone.0139434", "10.3389/fninf.2014.00059", "10.3390/informatics4030025", "10.1111/cgf.13528", "10.1002/nbm.3902", "10.1007/978-3-319-23344-4_29", "10.1007/978-3-319-15090-1_12", "10.1111/cgf.13703", "10.1111/cgf.13828", "10.1007/s12650-020-00642-1", "10.3390/a13120316"], "referencing": ["IKEY:4634616", "IKEY:219447", "IKEY:4015480", "IKEY:5290742", "IKEY:1372186", "IKEY:4069232", "IKEY:4392753", "IKEY:5710905", "IKEY:1580453", "IKEY:4015478", "IKEY:4015487", "IKEY:5290753", "IKEY:1532773", "IKEY:4658185", "IKEY:135913", "IKEY:1532772", "IKEY:567777", "IKEY:4634616", "IKEY:219447", "IKEY:4015480", "IKEY:5290742", "IKEY:1372186", "IKEY:4069232", "IKEY:4392753", "IKEY:5710905", "IKEY:1580453", "IKEY:4015478", "IKEY:4015487", "IKEY:5290753", "IKEY:1532773", "IKEY:4658185", "IKEY:135913", "IKEY:1532772", "IKEY:567777", "IKEY:4634616", "IKEY:219447", "IKEY:4015480", "IKEY:5290742", "IKEY:1372186", "IKEY:4069232", "IKEY:4392753", "IKEY:5710905", "IKEY:1580453", "IKEY:4015478", "IKEY:4015487", "IKEY:5290753", "IKEY:1532773", "IKEY:4658185", "IKEY:135913", "IKEY:1532772", "IKEY:567777", "10.1145/1404435.1404441", "10.1145/1185657.1185834", "10.1145/1053427.1053434", "10.1145/566570.566612", "10.1145/1111411.1111415", "10.1145/882262.882359", "10.1145/1044588.1044615", "10.1145/1837101.1837102", "10.1145/1179622.1179766", "10.1145/1140491.1140514", "10.1145/1186822.1073319", "10.1145/1230100.1230113", "10.1145/1730804.1730984", "10.1145/74333.74367", "10.1145/1179352.1141982", "10.1145/147156.147161", "10.1145/563858.563893", "10.1145/545265.545267", "10.1145/1141911.1142016", "10.1145/1281500.1281671", "10.1145/1404435.1404441", "10.1145/1185657.1185834", "10.1145/1053427.1053434", "10.1145/566570.566612", "10.1145/1111411.1111415", "10.1145/882262.882359", "10.1145/1044588.1044615", "10.1145/1837101.1837102", "10.1145/1179622.1179766", "10.1145/1140491.1140514", "10.1145/1186822.1073319", "10.1145/1230100.1230113", "10.1145/1730804.1730984", "10.1145/74333.74367", "10.1145/1179352.1141982", "10.1145/147156.147161", "10.1145/563858.563893", "10.1145/545265.545267", "10.1145/1141911.1142016", "10.1145/1281500.1281671", "10.1145/1404435.1404441", "10.1145/1185657.1185834", "10.1145/1053427.1053434", "10.1145/566570.566612", "10.1145/1111411.1111415", "10.1145/882262.882359", "10.1145/1044588.1044615", "10.1145/1837101.1837102", "10.1145/1179622.1179766", "10.1145/1140491.1140514", "10.1145/1186822.1073319", "10.1145/1230100.1230113", "10.1145/1730804.1730984", "10.1145/74333.74367", "10.1145/1179352.1141982", "10.1145/147156.147161", "10.1145/563858.563893", "10.1145/545265.545267", "10.1145/1141911.1142016", "10.1145/1281500.1281671", "10.1080/2151237X.2007.10129241", "10.1111/j.1467-8659.2009.01695.x", "10.1002/1522-2594(200010)44:4&lt;625::AID-MRM17&gt;3.0.CO;2-O", "10.1002/nbm.781", "10.3171/jns.2004.101.1.0066", "10.1002/1522-2594(200006)43:6&lt;921::AID-MRM23&gt;3.0.CO;2-I", "10.1038/331163a0", "10.1068/p3060", "10.1007/s00371-006-0052-0", "10.1080/2151237X.2007.10129241", "10.1111/j.1467-8659.2009.01695.x", "10.1002/1522-2594(200010)44:4&lt;625::AID-MRM17&gt;3.0.CO;2-O", "10.1002/nbm.781", "10.3171/jns.2004.101.1.0066", "10.1002/1522-2594(200006)43:6&lt;921::AID-MRM23&gt;3.0.CO;2-I", "10.1038/331163a0", "10.1068/p3060", "10.1007/s00371-006-0052-0", "10.1080/2151237X.2007.10129241", "10.1111/j.1467-8659.2009.01695.x", "10.1002/1522-2594(200010)44:4&lt;625::AID-MRM17&gt;3.0.CO;2-O", "10.1002/nbm.781", "10.3171/jns.2004.101.1.0066", "10.1002/1522-2594(200006)43:6&lt;921::AID-MRM23&gt;3.0.CO;2-I", "10.1038/331163a0", "10.1068/p3060", "10.1007/s00371-006-0052-0"]}, "10.1109/TVCG.2012.144": {"doi": "10.1109/TVCG.2012.144", "author": ["L. Zheng", "Y. Wu", "K. Ma"], "title": "Perceptually-Based Depth-Ordering Enhancement for Direct Volume Rendering", "year": "2013", "abstract": "Visualizing complex volume data usually renders selected parts of the volume semitransparently to see inner structures of the volume or provide a context. This presents a challenge for volume rendering methods to produce images with unambiguous depth-ordering perception. Existing methods use visual cues such as halos and shadows to enhance depth perception. Along with other limitations, these methods introduce redundant information and require additional overhead. This paper presents a new approach to enhancing depth-ordering perception of volume rendered images without using additional visual cues. We set up an energy function based on quantitative perception models to measure the quality of the images in terms of the effectiveness of depth-ordering and transparency perception as well as the faithfulness of the information revealed. Guided by the function, we use a conjugate gradient method to iteratively and judiciously enhance the results. Our method can complement existing systems for enhancing volume rendering results. The experimental results demonstrate the usefulness and effectiveness of our approach.", "keywords": ["conjugate gradient methods", "data visualisation", "rendering (computer graphics)", "perceptually based depth ordering enhancement", "direct volume rendering", "visualizing complex volume data", "energy function", "volume rendered images", "quantitative perception models", "transparency perception", "conjugate gradient method", "Rendering (computer graphics)", "Junctions", "Image color analysis", "Transfer functions", "Visualization", "Optimization", "Solid modeling", "Volume rendering", "depth ordering", "depth perception", "transparency", "visualization", "Algorithms", "Computer Graphics", "Depth Perception", "Humans", "Image Enhancement", "Image Interpretation, Computer-Assisted", "Imaging, Three-Dimensional", "Numerical Analysis, Computer-Assisted", "User-Computer Interface"], "referenced_by": ["IKEY:7938241", "IKEY:8115410", "IKEY:6620865", "IKEY:6875930", "IKEY:7055322", "IKEY:7272654", "IKEY:8478536", "10.1145/2504568", "10.1002/cav.1664", "10.1007/s41095-016-0035-7", "10.1016/j.compmedimag.2014.06.015", "10.1111/cgf.12633", "10.1111/cgf.12927", "10.1111/cgf.13169", "10.1111/cgf.13320", "10.1155/2016/4547138", "10.1016/j.jvlc.2018.08.010", "10.1007/978-1-4614-7485-2_2", "10.1007/978-3-030-34444-3_7"], "referencing": ["IKEY:1216223", "IKEY:942693", "IKEY:969118", "IKEY:856997", "IKEY:4658198", "IKEY:4276082", "IKEY:175805", "IKEY:4376160", "IKEY:5290740", "IKEY:4548689", "IKEY:5290739", "IKEY:5416704", "IKEY:5290742", "IKEY:597794", "IKEY:1250414", "IKEY:1196003", "IKEY:1372209", "IKEY:1216223", "IKEY:942693", "IKEY:969118", "IKEY:856997", "IKEY:4658198", "IKEY:4276082", "IKEY:175805", "IKEY:4376160", "IKEY:5290740", "IKEY:4548689", "IKEY:5290739", "IKEY:5416704", "IKEY:5290742", "IKEY:597794", "IKEY:1250414", "IKEY:1196003", "IKEY:1372209", "IKEY:1216223", "IKEY:942693", "IKEY:969118", "IKEY:856997", "IKEY:4658198", "IKEY:4276082", "IKEY:175805", "IKEY:4376160", "IKEY:5290740", "IKEY:4548689", "IKEY:5290739", "IKEY:5416704", "IKEY:5290742", "IKEY:597794", "IKEY:1250414", "IKEY:1196003", "IKEY:1372209", "10.1145/1462048.1462054", "10.1145/1836248.1836276", "10.1145/99307.99329", "10.1145/1462048.1462054", "10.1145/1836248.1836276", "10.1145/99307.99329", "10.1145/1462048.1462054", "10.1145/1836248.1836276", "10.1145/99307.99329", "10.1068/p3173", "10.1006/cviu.1999.0789", "10.1037/0033-295X.109.3.492", "10.1007/3-540-30790-7_12", "10.1214/ss/1177011454", "10.1068/p260419", "10.1148/radiographics.19.3.g99ma14745", "10.1007/978-1-84882-297-9", "10.1016/S0140-6736(97)08005-7", "10.1080/00140137008931118", "10.3758/BF03207164", "10.1016/0042-6989(94)90116-3", "10.1068/p3173", "10.1006/cviu.1999.0789", "10.1037/0033-295X.109.3.492", "10.1007/3-540-30790-7_12", "10.1214/ss/1177011454", "10.1068/p260419", "10.1148/radiographics.19.3.g99ma14745", "10.1007/978-1-84882-297-9", "10.1016/S0140-6736(97)08005-7", "10.1080/00140137008931118", "10.3758/BF03207164", "10.1016/0042-6989(94)90116-3", "10.1068/p3173", "10.1006/cviu.1999.0789", "10.1037/0033-295X.109.3.492", "10.1007/3-540-30790-7_12", "10.1214/ss/1177011454", "10.1068/p260419", "10.1148/radiographics.19.3.g99ma14745", "10.1007/978-1-84882-297-9", "10.1016/S0140-6736(97)08005-7", "10.1080/00140137008931118", "10.3758/BF03207164", "10.1016/0042-6989(94)90116-3"]}, "10.1109/TVCG.2012.129": {"doi": "10.1109/TVCG.2012.129", "author": ["S. Du", "S. Hu", "R. R. Martin"], "title": "Semiregular Solid Texturing from 2D Image Exemplars", "year": "2013", "abstract": "Solid textures, comprising 3D particles embedded in a matrix in a regular or semiregular pattern, are common in natural and man-made materials, such as brickwork, stone walls, plant cells in a leaf, etc. We present a novel technique for synthesizing such textures, starting from 2D image exemplars which provide cross-sections of the desired volume texture. The shapes and colors of typical particles embedded in the structure are estimated from their 2D cross-sections. Particle positions in the texture images are also used to guide spatial placement of the 3D particles during synthesis of the 3D texture. Our experiments demonstrate that our algorithm can produce higher quality structures than previous approaches; they are both compatible with the input images, and have a plausible 3D nature.", "keywords": ["embedded systems", "image texture", "matrix algebra", "solid modelling", "semiregular solid texturing", "2D image exemplars", "3D particles", "volume texture", "2D cross-sections", "Three dimensional displays", "Solids", "Shape", "Color", "Image reconstruction", "Image color analysis", "Solid texture", "texture generation", "semiregular texture", "Algorithms", "Computer Graphics", "Image Enhancement", "Image Interpretation, Computer-Assisted", "Imaging, Three-Dimensional", "Pattern Recognition, Automated", "User-Computer Interface"], "referenced_by": ["10.1007/s00371-013-0843-z", "10.1007/s11390-013-1381-x", "10.1016/B978-0-12-800645-0.50027-0", "10.1016/j.cagd.2017.03.015", "10.1016/j.gmod.2012.10.006", "10.1111/cgf.12260", "10.1111/cgf.13023", "10.1155/2013/416186", "10.1364/OE.25.033202", "10.1007/978-3-319-12286-1_31", "10.1007/s00371-014-0951-4", "10.1108/RPJ-03-2019-0070"], "referencing": ["IKEY:4069245", "IKEY:736470", "IKEY:5416703", "IKEY:5374358", "IKEY:5557871", "IKEY:537718", "IKEY:4069245", "IKEY:736470", "IKEY:5416703", "IKEY:5374358", "IKEY:5557871", "IKEY:537718", "IKEY:4069245", "IKEY:736470", "IKEY:5416703", "IKEY:5374358", "IKEY:5557871", "IKEY:537718", "10.1145/2010324.1964946", "10.1145/1073204.1073263", "10.1145/1186822.1073261", "10.1145/1618452.1618456", "10.1145/882262.882266", "10.1145/1778765.1778823", "10.1145/2070781.2024201", "10.1145/2010324.1964957", "10.1145/566654.566581", "10.1145/1015706.1015723", "10.1145/1360612.1360653", "10.1145/344779.344987", "10.1145/1882261.1866202", "10.1145/1278760.1278765", "10.1145/344779.344859", "10.1145/1360612.1360653", "10.1145/1618452.1618464", "10.1145/325165.325246", "10.1145/325165.325247", "10.1145/1276377.1276380", "10.1145/1015706.1015724", "10.1145/1015706.1015731", "10.1145/237170.237267", "10.1145/2010324.1964946", "10.1145/1073204.1073263", "10.1145/1186822.1073261", "10.1145/1618452.1618456", "10.1145/882262.882266", "10.1145/1778765.1778823", "10.1145/2070781.2024201", "10.1145/2010324.1964957", "10.1145/566654.566581", "10.1145/1015706.1015723", "10.1145/1360612.1360653", "10.1145/344779.344987", "10.1145/1882261.1866202", "10.1145/1278760.1278765", "10.1145/344779.344859", "10.1145/1360612.1360653", "10.1145/1618452.1618464", "10.1145/325165.325246", "10.1145/325165.325247", "10.1145/1276377.1276380", "10.1145/1015706.1015724", "10.1145/1015706.1015731", "10.1145/237170.237267", "10.1145/2010324.1964946", "10.1145/1073204.1073263", "10.1145/1186822.1073261", "10.1145/1618452.1618456", "10.1145/882262.882266", "10.1145/1778765.1778823", "10.1145/2070781.2024201", "10.1145/2010324.1964957", "10.1145/566654.566581", "10.1145/1015706.1015723", "10.1145/1360612.1360653", "10.1145/344779.344987", "10.1145/1882261.1866202", "10.1145/1278760.1278765", "10.1145/344779.344859", "10.1145/1360612.1360653", "10.1145/1618452.1618464", "10.1145/325165.325246", "10.1145/325165.325247", "10.1145/1276377.1276380", "10.1145/1015706.1015724", "10.1145/1015706.1015731", "10.1145/237170.237267", "10.1016/j.gmod.2010.10.006", "10.1111/j.1467-8659.2007.01087.x", "10.1111/1467-8659.00600", "10.1007/s00371-011-0635-2", "10.1007/s00371-011-0621-8", "10.1111/j.1467-8659.2008.01254.x", "10.1016/j.gmod.2010.10.006", "10.1111/j.1467-8659.2007.01087.x", "10.1111/1467-8659.00600", "10.1007/s00371-011-0635-2", "10.1007/s00371-011-0621-8", "10.1111/j.1467-8659.2008.01254.x", "10.1016/j.gmod.2010.10.006", "10.1111/j.1467-8659.2007.01087.x", "10.1111/1467-8659.00600", "10.1007/s00371-011-0635-2", "10.1007/s00371-011-0621-8", "10.1111/j.1467-8659.2008.01254.x"]}, "10.1109/TVCG.2012.128": {"doi": "10.1109/TVCG.2012.128", "author": ["T. N. Dang", "A. Anand", "L. Wilkinson"], "title": "TimeSeer: Scagnostics for High-Dimensional Time Series", "year": "2013", "abstract": "We introduce a method (Scagnostic time series) and an application (TimeSeer) for organizing multivariate time series and for guiding interactive exploration through high-dimensional data. The method is based on nine characterizations of the 2D distributions of orthogonal pairwise projections on a set of points in multidimensional euclidean space. These characterizations include measures, such as, density, skewness, shape, outliers, and texture. Working directly with these Scagnostic measures, we can locate anomalous or interesting subseries for further analysis. Our application is designed to handle the types of doubly multivariate data series that are often found in security, financial, social, and other sectors.", "keywords": ["data analysis", "time series", "TimeSeer", "high-dimensional time series scagnostics", "multivariate time series", "interactive exploration", "2D distributions", "orthogonal pairwise projections", "multidimensional euclidean space", "density", "skewness", "shape", "outliers", "texture", "doubly multivariate data series", "social sectors", "financial sectors", "security sectors", "Time series analysis", "Lenses", "Shape", "Length measurement", "Employment", "Density measurement", "Visualization", "Scagnostics", "scatterplot matrix", "high-dimensional visual analytics", "multiple time series", "Algorithms", "Computer Graphics", "Computer Simulation", "Image Interpretation, Computer-Assisted", "Imaging, Three-Dimensional", "Models, Statistical", "Multivariate Analysis", "Reproducibility of Results", "Sensitivity and Specificity", "Software", "User-Computer Interface"], "referenced_by": ["IKEY:6787139", "IKEY:6875982", "IKEY:7784854", "IKEY:7883514", "IKEY:8622445", "IKEY:8622092", "IKEY:8802440", "IKEY:8807247", "IKEY:8933670", "IKEY:8490694", "IKEY:9006559", "IKEY:9006542", "IKEY:9086210", "IKEY:9240550", "10.1145/3182187", "10.1007/s11390-013-1383-8", "10.1111/cgf.12646", "10.1111/cgf.12882", "10.1111/cgf.13446", "10.1111/cgf.13404", "10.1111/cgf.13453", "10.1007/978-3-030-17872-7_17", "10.1007/s00371-019-01673-y", "10.1520/SSMS20190029", "10.1007/978-3-030-33720-9_25", "10.1002/9781118445112.stat08297"], "referencing": ["IKEY:1532136", "IKEY:4658160", "IKEY:801851", "IKEY:1532122", "IKEY:963273", "IKEY:1532142", "IKEY:1703359", "IKEY:1560021", "IKEY:885098", "IKEY:1056714", "IKEY:4035766", "IKEY:4658136", "IKEY:5613439", "IKEY:1532136", "IKEY:4658160", "IKEY:801851", "IKEY:1532122", "IKEY:963273", "IKEY:1532142", "IKEY:1703359", "IKEY:1560021", "IKEY:885098", "IKEY:1056714", "IKEY:4035766", "IKEY:4658136", "IKEY:5613439", "IKEY:1532136", "IKEY:4658160", "IKEY:801851", "IKEY:1532122", "IKEY:963273", "IKEY:1532142", "IKEY:1703359", "IKEY:1560021", "IKEY:885098", "IKEY:1056714", "IKEY:4035766", "IKEY:4658136", "IKEY:5613439", "10.1145/1518701.1518897", "10.1145/775047.775128", "10.1145/180171.180173", "10.1145/1014052.1014104", "10.1145/1357054.1357286", "10.1145/312129.312268", "10.1145/191666.191776", "10.1145/347090.347192", "10.1145/956750.956808", "10.1145/1518701.1518897", "10.1145/775047.775128", "10.1145/180171.180173", "10.1145/1014052.1014104", "10.1145/1357054.1357286", "10.1145/312129.312268", "10.1145/191666.191776", "10.1145/347090.347192", "10.1145/956750.956808", "10.1145/1518701.1518897", "10.1145/775047.775128", "10.1145/180171.180173", "10.1145/1014052.1014104", "10.1145/1357054.1357286", "10.1145/312129.312268", "10.1145/191666.191776", "10.1145/347090.347192", "10.1145/956750.956808", "10.1016/j.cag.2007.01.030", "10.1057/palgrave.ivs.9500165", "10.2307/2683467", "10.2307/2346439", "10.1007/BF02618468", "10.1080/01621459.1989.10478797", "10.1057/palgrave.ivs.9500061", "10.1086/368480", "10.1177/1473871611416549", "10.1057/palgrave.ivs.9500091", "10.1007/b102382", "10.1007/s10618-007-0070-1", "10.1007/s00357-003-0004-6", "10.2307/2289444", "10.1016/j.cag.2007.01.030", "10.1057/palgrave.ivs.9500165", "10.2307/2683467", "10.2307/2346439", "10.1007/BF02618468", "10.1080/01621459.1989.10478797", "10.1057/palgrave.ivs.9500061", "10.1086/368480", "10.1177/1473871611416549", "10.1057/palgrave.ivs.9500091", "10.1007/b102382", "10.1007/s10618-007-0070-1", "10.1007/s00357-003-0004-6", "10.2307/2289444", "10.1016/j.cag.2007.01.030", "10.1057/palgrave.ivs.9500165", "10.2307/2683467", "10.2307/2346439", "10.1007/BF02618468", "10.1080/01621459.1989.10478797", "10.1057/palgrave.ivs.9500061", "10.1086/368480", "10.1177/1473871611416549", "10.1057/palgrave.ivs.9500091", "10.1007/b102382", "10.1007/s10618-007-0070-1", "10.1007/s00357-003-0004-6", "10.2307/2289444"]}, "10.1109/TVCG.2012.127": {"doi": "10.1109/TVCG.2012.127", "author": ["D. Li", "X. Sun", "Z. Ren", "S. Lin", "Y. Tong", "B. Guo", "K. Zhou"], "title": "TransCut: Interactive Rendering of Translucent Cutouts", "year": "2013", "abstract": "We present TransCut, a technique for interactive rendering of translucent objects undergoing fracturing and cutting operations. As the object is fractured or cut open, the user can directly examine and intuitively understand the complex translucent interior, as well as edit material properties through painting on cross sections and recombining the broken pieces-all with immediate and realistic visual feedback. This new mode of interaction with translucent volumes is made possible with two technical contributions. The first is a novel solver for the diffusion equation (DE) over a tetrahedral mesh that produces high-quality results comparable to the state-of-art finite element method (FEM) of Arbree et al. [1] but at substantially higher speeds. This accuracy and efficiency is obtained by computing the discrete divergences of the diffusion equation and constructing the DE matrix using analytic formulas derived for linear finite elements. The second contribution is a multiresolution algorithm to significantly accelerate our DE solver while adapting to the frequent changes in topological structure of dynamic objects. The entire multiresolution DE solver is highly parallel and easily implemented on the GPU. We believe TransCut provides a novel visual effect for heterogeneous translucent objects undergoing fracturing and cutting operations.", "keywords": ["finite element analysis", "interactive systems", "matrix algebra", "rendering (computer graphics)", "TransCut", "interactive rendering", "translucent cutouts", "translucent objects", "material properties", "translucent volumes", "diffusion equation", "DE", "tetrahedral mesh", "finite element method", "FEM", "multiresolution algorithm", "GPU", "Mathematical model", "Equations", "Rendering (computer graphics)", "Scattering", "Materials", "Approximation methods", "Subsurface scattering", "heterogeneous material", "diffusion equation", "multiresolution", "Algorithms", "Computer Graphics", "Image Enhancement", "Image Interpretation, Computer-Assisted", "Imaging, Three-Dimensional", "Pattern Recognition, Automated", "Refractometry", "User-Computer Interface"], "referenced_by": ["IKEY:6994841", "10.1007/s00371-014-0952-3", "10.1007/s00371-016-1207-2", "10.1007/s00530-017-0564-7", "10.1007/s12650-014-0207-4", "10.1111/cgf.12342", "10.1111/cgf.12529", "10.1007/978-3-642-35777-0_5"], "referencing": ["IKEY:6086521", "IKEY:5582083", "IKEY:6086521", "IKEY:5582083", "IKEY:6086521", "IKEY:5582083", "10.1145/383259.383319", "10.1145/1073204.1073308", "10.1145/1457515.1409093", "10.1145/2010324.1964951", "10.1145/990002.990004", "10.1145/1073204.1073333", "10.1145/1342250.1342263", "10.1145/1276377.1276448", "10.1145/1330511.1330520", "10.1145/882262.882290", "10.1145/1141911.1142001", "10.1145/311535.311550", "10.1145/566570.566579", "10.1145/1015706.1015723", "10.1145/1882261.1866202", "10.1145/1599470.1599492", "10.1145/311535.311560", "10.1145/344779.344824", "10.1145/383259.383319", "10.1145/1073204.1073308", "10.1145/1457515.1409093", "10.1145/2010324.1964951", "10.1145/990002.990004", "10.1145/1073204.1073333", "10.1145/1342250.1342263", "10.1145/1276377.1276448", "10.1145/1330511.1330520", "10.1145/882262.882290", "10.1145/1141911.1142001", "10.1145/311535.311550", "10.1145/566570.566579", "10.1145/1015706.1015723", "10.1145/1882261.1866202", "10.1145/1599470.1599492", "10.1145/311535.311560", "10.1145/344779.344824", "10.1145/383259.383319", "10.1145/1073204.1073308", "10.1145/1457515.1409093", "10.1145/2010324.1964951", "10.1145/990002.990004", "10.1145/1073204.1073333", "10.1145/1342250.1342263", "10.1145/1276377.1276448", "10.1145/1330511.1330520", "10.1145/882262.882290", "10.1145/1141911.1142001", "10.1145/311535.311550", "10.1145/566570.566579", "10.1145/1015706.1015723", "10.1145/1882261.1866202", "10.1145/1599470.1599492", "10.1145/311535.311560", "10.1145/344779.344824", "10.1007/3-540-29090-7_9", "10.1088/0031-9155/50/4/R01", "10.1111/j.1467-8659.2009.01619.x", "10.1007/3-540-29090-7_9", "10.1088/0031-9155/50/4/R01", "10.1111/j.1467-8659.2009.01619.x", "10.1007/3-540-29090-7_9", "10.1088/0031-9155/50/4/R01", "10.1111/j.1467-8659.2009.01619.x"]}, "10.1109/TVCG.2012.110": {"doi": "10.1109/TVCG.2012.110", "author": ["J. Kehrer", "H. Hauser"], "title": "Visualization and Visual Analysis of Multifaceted Scientific Data: A Survey", "year": "2013", "abstract": "Visualization and visual analysis play important roles in exploring, analyzing, and presenting scientific data. In many disciplines, data and model scenarios are becoming multifaceted: data are often spatiotemporal and multivariate; they stem from different data sources (multimodal data), from multiple simulation runs (multirun/ensemble data), or from multiphysics simulations of interacting phenomena (multimodel data resulting from coupled simulation models). Also, data can be of different dimensionality or structured on various types of grids that need to be related or fused in the visualization. This heterogeneity of data characteristics presents new opportunities as well as technical challenges for visualization research. Visualization and interaction techniques are thus often combined with computational analysis. In this survey, we study existing methods for visualization and interactive visual analysis of multifaceted scientific data. Based on a thorough literature review, a categorization of approaches is proposed. We cover a wide range of fields and discuss to which degree the different challenges are matched with existing solutions for visualization and visual analysis. This leads to conclusions with respect to promising research directions, for instance, to pursue new solutions for multirun and multimodel data as well as techniques that support a multitude of facets.", "keywords": ["data visualisation", "multifaceted scientific data", "spatiotemporal data", "multivariate data", "data sources", "multimodel data", "multiphysics simulations", "multirun-ensemble data", "data characteristics heterogeneity", "visualization techniques", "computational analysis", "interactive visual analysis", "Data visualization", "Visualization", "Data models", "Computational modeling", "Data mining", "Atmospheric modeling", "Solid modeling", "Visualization", "interactive visual analysis", "multirun", "multimodel", "multimodal", "multivariate", "spatiotemporal data", "Algorithms", "Computer Graphics", "Computer Simulation", "Database Management Systems", "Databases, Factual", "Image Interpretation, Computer-Assisted", "Imaging, Three-Dimensional", "Models, Theoretical", "User-Computer Interface"], "referenced_by": [], "referencing": ["10.1145/637357.637361", "10.1145/1809400.1809404", "10.1145/1838544.1838551", "10.1145/1980462.1980470", "10.1145/827051.827054", "10.1145/22627.22342", "10.1145/230562.230563", "10.1145/238386.238587", "10.1145/637357.637361", "10.1145/1809400.1809404", "10.1145/1838544.1838551", "10.1145/1980462.1980470", "10.1145/827051.827054", "10.1145/22627.22342", "10.1145/230562.230563", "10.1145/238386.238587", "10.1145/637357.637361", "10.1145/1809400.1809404", "10.1145/1838544.1838551", "10.1145/1980462.1980470", "10.1145/827051.827054", "10.1145/22627.22342", "10.1145/230562.230563", "10.1145/238386.238587", "10.2481/dsj.3.153", "10.1057/palgrave.ivs.9500006", "10.1057/palgrave.ivs.9500020", "10.1057/ivs.2008.23", "10.1016/j.cag.2007.01.030", "10.1111/j.1467-8659.2009.01429.x", "10.1007/BF00547132", "10.1111/j.1467-8659.2009.01697.x", "10.1111/j.1467-8659.2009.01677.x", "10.1177/1473871611416549", "10.1137/0906011", "10.1080/00401706.1987.10488204", "10.1111/j.1467-8659.2009.01684.x", "10.1111/j.1467-8659.2011.01940.x", "10.1007/978-0-387-84858-7", "10.1007/978-3-540-33037-0_8", "10.1057/palgrave.ivs.9500024", "10.1111/j.1467-8659.2009.01664.x", "10.1057/palgrave.ivs.9500061", "10.2307/143141", "10.1111/j.1467-8659.2004.00753.x", "10.1016/j.engappai.2010.09.007", "10.1111/j.1467-8659.2009.01440.x", "10.1111/j.1467-8659.2009.01465.x", "10.1007/BF01898350", "10.1111/j.1467-8659.2008.01207.x", "10.1111/j.1467-8659.2003.00723.x", "10.1007/BF02915277", "10.1057/palgrave.ivs.9500040", "10.1007/s00371-010-0541-z", "10.1007/s003710050111", "10.2307/2288400", "10.1111/1467-8659.00356", "10.1559/1523040054738936", "10.2307/2683468", "10.2481/dsj.3.153", "10.1057/palgrave.ivs.9500006", "10.1057/palgrave.ivs.9500020", "10.1057/ivs.2008.23", "10.1016/j.cag.2007.01.030", "10.1111/j.1467-8659.2009.01429.x", "10.1007/BF00547132", "10.1111/j.1467-8659.2009.01697.x", "10.1111/j.1467-8659.2009.01677.x", "10.1177/1473871611416549", "10.1137/0906011", "10.1080/00401706.1987.10488204", "10.1111/j.1467-8659.2009.01684.x", "10.1111/j.1467-8659.2011.01940.x", "10.1007/978-0-387-84858-7", "10.1007/978-3-540-33037-0_8", "10.1057/palgrave.ivs.9500024", "10.1111/j.1467-8659.2009.01664.x", "10.1057/palgrave.ivs.9500061", "10.2307/143141", "10.1111/j.1467-8659.2004.00753.x", "10.1016/j.engappai.2010.09.007", "10.1111/j.1467-8659.2009.01440.x", "10.1111/j.1467-8659.2009.01465.x", "10.1007/BF01898350", "10.1111/j.1467-8659.2008.01207.x", "10.1111/j.1467-8659.2003.00723.x", "10.1007/BF02915277", "10.1057/palgrave.ivs.9500040", "10.1007/s00371-010-0541-z", "10.1007/s003710050111", "10.2307/2288400", "10.1111/1467-8659.00356", "10.1559/1523040054738936", "10.2307/2683468", "10.2481/dsj.3.153", "10.1057/palgrave.ivs.9500006", "10.1057/palgrave.ivs.9500020", "10.1057/ivs.2008.23", "10.1016/j.cag.2007.01.030", "10.1111/j.1467-8659.2009.01429.x", "10.1007/BF00547132", "10.1111/j.1467-8659.2009.01697.x", "10.1111/j.1467-8659.2009.01677.x", "10.1177/1473871611416549", "10.1137/0906011", "10.1080/00401706.1987.10488204", "10.1111/j.1467-8659.2009.01684.x", "10.1111/j.1467-8659.2011.01940.x", "10.1007/978-0-387-84858-7", "10.1007/978-3-540-33037-0_8", "10.1057/palgrave.ivs.9500024", "10.1111/j.1467-8659.2009.01664.x", "10.1057/palgrave.ivs.9500061", "10.2307/143141", "10.1111/j.1467-8659.2004.00753.x", "10.1016/j.engappai.2010.09.007", "10.1111/j.1467-8659.2009.01440.x", "10.1111/j.1467-8659.2009.01465.x", "10.1007/BF01898350", "10.1111/j.1467-8659.2008.01207.x", "10.1111/j.1467-8659.2003.00723.x", "10.1007/BF02915277", "10.1057/palgrave.ivs.9500040", "10.1007/s00371-010-0541-z", "10.1007/s003710050111", "10.2307/2288400", "10.1111/1467-8659.00356", "10.1559/1523040054738936", "10.2307/2683468"]}, "10.1109/TVCG.2012.120": {"doi": "10.1109/TVCG.2012.120", "author": ["P. Oesterling", "C. Heine", "G. H. Weber", "G. Scheuermann"], "title": "Visualizing nD Point Clouds as Topological Landscape Profiles to Guide Local Data Analysis", "year": "2013", "abstract": "Analyzing high-dimensional point clouds is a classical challenge in visual analytics. Traditional techniques, such as projections or axis-based techniques, suffer from projection artifacts, occlusion, and visual complexity. We propose to split data analysis into two parts to address these shortcomings. First, a structural overview phase abstracts data by its density distribution. This phase performs topological analysis to support accurate and nonoverlapping presentation of the high-dimensional cluster structure as a topological landscape profile. Utilizing a landscape metaphor, it presents clusters and their nesting as hills whose height, width, and shape reflect cluster coherence, size, and stability, respectively. A second local analysis phase utilizes this global structural knowledge to select individual clusters or point sets for further, localized data analysis. Focusing on structural entities significantly reduces visual clutter in established geometric visualizations and permits a clearer, more thorough data analysis. This analysis complements the global topological perspective and enables the user to study subspaces or geometric properties, such as shape.", "keywords": ["data analysis", "data visualisation", "topology", "topological landscape profiles", "visual analytics", "density distribution", "global structural knowledge", "geometric visualizations", "nD point clouds visualization", "local data analysis", "projection artifacts", "occlusion", "visual complexity", "high-dimensional cluster structure", "Visualization", "Vegetation", "Data visualization", "Shape", "Density functional theory", "Image color analysis", "Topology", "Point clouds", "high-dimensional data", "cluster analysis", "dimension reduction", "scalar topology", "and visual metaphors", "Algorithms", "Computer Graphics", "Image Enhancement", "Image Interpretation, Computer-Assisted", "Imaging, Three-Dimensional", "Information Storage and Retrieval", "Pattern Recognition, Automated", "Reproducibility of Results", "Sensitivity and Specificity", "Signal Processing, Computer-Assisted", "User-Computer Interface"], "referenced_by": ["IKEY:7818971", "IKEY:7156387", "IKEY:7784854", "10.1007/978-3-319-44684-4_5", "10.1007/978-3-319-44684-4_6", "10.1007/978-3-662-43968-5_4", "10.1016/j.cag.2014.02.005", "10.1111/cgf.12933", "10.1111/cgf.13396", "10.1007/978-3-319-12655-5_4"], "referencing": ["IKEY:146402", "IKEY:5652940", "IKEY:5613467", "IKEY:4376132", "IKEY:163414", "IKEY:5613436", "IKEY:1372235", "IKEY:5290728", "IKEY:4269947", "IKEY:856996", "IKEY:5708142", "IKEY:545307", "IKEY:809866", "IKEY:1532138", "IKEY:4015444", "IKEY:4376169", "IKEY:146402", "IKEY:5652940", "IKEY:5613467", "IKEY:4376132", "IKEY:163414", "IKEY:5613436", "IKEY:1372235", "IKEY:5290728", "IKEY:4269947", "IKEY:856996", "IKEY:5708142", "IKEY:545307", "IKEY:809866", "IKEY:1532138", "IKEY:4015444", "IKEY:4376169", "IKEY:146402", "IKEY:5652940", "IKEY:5613467", "IKEY:4376132", "IKEY:163414", "IKEY:5613436", "IKEY:1372235", "IKEY:5290728", "IKEY:4269947", "IKEY:856996", "IKEY:5708142", "IKEY:545307", "IKEY:809866", "IKEY:1532138", "IKEY:4015444", "IKEY:4376169", "10.1145/102377.115768", "10.1145/142750.143054", "10.1145/302979.303148", "10.1145/304182.304187", "10.1145/102377.115768", "10.1145/142750.143054", "10.1145/302979.303148", "10.1145/304182.304187", "10.1145/102377.115768", "10.1145/142750.143054", "10.1145/302979.303148", "10.1145/304182.304187", "10.1111/j.1467-8659.2009.01706.x", "10.1126/science.290.5500.2319", "10.1007/s00454-002-2885-2", "10.1007/978-3-642-56927-2", "10.1016/S0925-7721(02)00093-7", "10.1016/S0097-8493(02)00283-2", "10.1080/00401706.1987.10488204", "10.1111/j.1467-8659.2011.01898.x", "10.2307/2685881", "10.1007/978-1-4757-6465-9", "10.1007/s00454-006-1276-5", "10.1111/j.1467-8659.2009.01706.x", "10.1126/science.290.5500.2319", "10.1007/s00454-002-2885-2", "10.1007/978-3-642-56927-2", "10.1016/S0925-7721(02)00093-7", "10.1016/S0097-8493(02)00283-2", "10.1080/00401706.1987.10488204", "10.1111/j.1467-8659.2011.01898.x", "10.2307/2685881", "10.1007/978-1-4757-6465-9", "10.1007/s00454-006-1276-5", "10.1111/j.1467-8659.2009.01706.x", "10.1126/science.290.5500.2319", "10.1007/s00454-002-2885-2", "10.1007/978-3-642-56927-2", "10.1016/S0925-7721(02)00093-7", "10.1016/S0097-8493(02)00283-2", "10.1080/00401706.1987.10488204", "10.1111/j.1467-8659.2011.01898.x", "10.2307/2685881", "10.1007/978-1-4757-6465-9", "10.1007/s00454-006-1276-5"]}, "10.1109/TVCG.2012.62": {"doi": "10.1109/TVCG.2012.62", "author": ["H. Bhatia", "G. Norgard", "V. Pascucci", "P. Bremer"], "title": "Comments on the \"Meshless Helmholtz-Hodge Decomposition\"", "year": "2013", "abstract": "The Helmholtz-Hodge decomposition (HHD) is one of the fundamental theorems of fluids describing the decomposition of a flow field into its divergence-free, curl-free, and harmonic components. Solving for the HHD is intimately connected to the choice of boundary conditions which determine the uniqueness and orthogonality of the decomposition. This article points out that one of the boundary conditions used in a recent paper \u201cMeshless Helmholtz-Hodge Decomposition\u201d [5] is, in general, invalid and provides an analytical example demonstrating the problem. We hope that this clarification on the theory will foster further research in this area and prevent undue problems in applying and extending the original approach.", "keywords": ["decomposition", "Helmholtz equations", "meshless Helmholtz-Hodge decomposition", "HHD", "flow field", "divergence-free", "curl-free", "harmonic components", "boundary conditions", "Boundary conditions", "Harmonic analysis", "Computational modeling", "Vector fields", "boundary conditions", "Helmholtz-Hodge decomposition.", "Algorithms", "Computer Graphics", "Models, Theoretical", "Rheology"], "referenced_by": ["IKEY:6365629", "10.1007/s10035-017-0714-9", "10.1007/s10035-018-0815-0"], "referencing": ["IKEY:5200996", "IKEY:5200996", "IKEY:5200996", "10.1145/882262.882290", "10.1145/882262.882290", "10.1145/882262.882290", "10.1002/fld.598", "10.1007/978-3-7091-6783-0_15", "10.1002/fld.598", "10.1007/978-3-7091-6783-0_15", "10.1002/fld.598", "10.1007/978-3-7091-6783-0_15"]}}